{
  "Algebra 1": {
    "Module 0": [
      {
        "id": "ALG1-0.1-B1",
        "type": "template",
        "objective": "Adding Fractions",
        "difficulty": "basic",
        "variables": { 
          "a": { "min": -10, "max": 10, "exclude": [0] } , 
          "b": { "min": 2, "max": 12, "exclude": ["a"]}, 
          "c": { "min": -10, "max": 10, "exclude": [0] }, 
          "d": { "min": 2, "max": 12, "exclude": ["c"] } },
        "question": "Evaluate: \\( \\frac{{{a}}}{{{b}}} + \\frac{{{c}}}{{{d}}} \\).",
        "answerFormula": "simplifyFraction(a*d + b*c, b*d)"
      },
      {
        "id": "ALG1-0.1-B2",
        "type": "template",
        "objective": "Subtracting Fractions",
        "difficulty": "basic",
        "variables": { 
          "a": { "min": -10, "max": 10, "exclude": [0] } , 
          "b": { "min": 2, "max": 12, "exclude": ["a"]}, 
          "c": { "min": -10, "max": 10, "exclude": [0] }, 
          "d": { "min": 2, "max": 12, "exclude": ["c"] } },
        "question": "Evaluate: \\( \\frac{{{a}}}{{{b}}} - \\frac{{{c}}}{{{d}}} \\).",
        "answerFormula": "simplifyFraction(a*d - b*c, b*d)"
      },
      {
        "id": "ALG1-0.1-B3",
        "type": "template",
        "objective": "Multiplying Fractions",
        "difficulty": "basic",
        "variables": { 
          "a": { "min": -10, "max": 10, "exclude": [0] } , 
          "b": { "min": 2, "max": 12, "exclude": ["a"]}, 
          "c": { "min": -10, "max": 10, "exclude": [0] }, 
          "d": { "min": 2, "max": 12, "exclude": ["c"] } },
        "question": "Evaluate: \\( \\frac{{{a}}}{{{b}}} \\times \\frac{{{c}}}{{{d}}} \\).",
        "answerFormula": "simplifyFraction(a*c, b*d)"
      },
      
      {
        "id": "ALG1-0.1-B4",
        "type": "template",
        "objective": "Dividing Fractions",
        "difficulty": "basic",
        "variables": { 
          "a": { "min": -10, "max": 10, "exclude": [0] } , 
          "b": { "min": 2, "max": 12, "exclude": ["a"]}, 
          "c": { "min": -10, "max": 10, "exclude": [0] }, 
          "d": { "min": 2, "max": 12, "exclude": ["c"] } },
        "question": "Evaluate: \\( \\frac{{{a}}}{{{b}}} \\div \\frac{{{c}}}{{{d}}} \\).",
        "answerFormula": "simplifyFraction(a*d, b*c)"
      },
      {
        "id": "ALG1-0.1-B5",
        "type": "template",
        "objective": "Adding Fractions and Integers",
        "difficulty": "basic",
        "variables": { "a": { "min": -10, "max": 10, "exclude":[0] }, "b": { "min": 2, "max": 20, "exclude":["a"] }, "c": { "min": -10, "max": 10 } },
        "question": "Add: \\( \\frac{{{a}}}{{{b}}} + ({c}) \\).",
        "answerFormula": "simplifyFraction(a + b*c, b)"
      },
      {
        "id": "ALG1-0.1-B6",
        "type": "template",
        "objective": "Subtracting Fractions and Integers",
        "difficulty": "basic",
        "variables": { "a": { "min": -10, "max": 10, "exclude":[0] }, "b": { "min": 2, "max": 20, "exclude":["a"] }, "c": { "min": -10, "max": 10 } },
        "question": "Subtract: \\( {c} - \\frac{{{a}}}{{{b}}} \\).",
        "answerFormula": "simplifyFraction(c*b - a, b)"
      },
      {
        "id": "ALG1-0.1-B7",
        "type": "template",
        "objective": "Multiplying Fractions and Integers",
        "difficulty": "basic",
        "variables": { "a": { "min": -10, "max": 10, "exclude":[0] }, "b": { "min": 2, "max": 20, "exclude":["a"] }, "c": { "min": -10, "max": 10 } },
        "question": "Multiply: \\( {c} \\times \\frac{{{a}}}{{{b}}} \\).",
        "answerFormula": "simplifyFraction(a*c, b)"
      },
      {
        "id": "ALG1-0.1-B8",
        "type": "template",
        "objective": "Dividing Fractions and Integers",
        "difficulty": "basic",
        "variables": { "a": { "min": -10, "max": 10, "exclude":[0] }, "b": { "min": 2, "max": 20, "exclude":["a"] }, "c": { "min": -10, "max": 10 } },
        "question": "Divide: \\( {c} \\div \\frac{{{a}}}{{{b}}} \\).",
        "answerFormula": "simplifyFraction(c*b, a)"
      },
      {
        "id": "ALG1-0.2-I1",
        "type": "template",
        "objective": "Subtracting Fractions",
        "difficulty": "intermediate",
        "variables": { "a": { "min": 5, "max": 12 }, "b": { "min": 6, "max": 15,"exclude":["a"] }, "c": { "min": 1, "max": 5 }, "d": { "min": 2, "max": 10, "exclude":["c"] } },
        "question": "A tank is \\({a}/{b}\\) full of water. After using \\({c}/{d}\\) of the water, how much water is left in the tank?",
        "answerFormula": "simplifyFraction(a*d - b*c, b*d)"
      },
      {
        "id": "ALG1-0.2-I2",
        "type": "template",
        "objective": "Multiplying Fractions",
        "difficulty": "intermediate",
        "variables": { "a": { "min": 5, "max": 12 }, "b": { "min": 6, "max": 15,"exclude":["a"] }, "c": { "min": 1, "max": 5 }, "d": { "min": 2, "max": 10, "exclude":["c"] } },
        "question": "A recipe calls for \\({a}/{b}\\) cups of sugar per batch. If you make \\({c}/{d}\\) of a batch, how much sugar do you need?",
        "answerFormula": "simplifyFraction(a*c, b*d)"
      },
      {
        "id": "ALG1-0.2-I3",
        "type": "template",
        "objective": "Dividing Fractions",
        "difficulty": "intermediate",
        "variables": { "a": { "min": 1, "max": 7 }, "b": { "min": 2, "max": 12, "exclude":["a"] }, "c": { "min": 1, "max": 5 } },
        "question": "You have \\({a}/{b}\\) of a chocolate bar and want to share it equally among \\({c}\\) friends. How much chocolate does each friend get?",
        "answerFormula": "simplifyFraction(a, b*c)"
      },
      {
        "id": "ALG1-0.3-A1",
        "type": "template",
        "objective": "Multi-step Fraction Operations",
        "difficulty": "advanced",
        "variables": { "a": { "min": 1, "max": 5 }, "b": { "min": 2, "max": 12, "exclude":["a"] }, "c": { "min": 1, "max": 7 }, "d": { "min": 2, "max": 10, "exclude":["c"] }, "e": { "min": 1, "max": 4 }, "f": { "min": 2, "max": 8, "exclude":["e"] } },
        "question": "Liam baked \\({a}/{b}\\) of a cake on Monday and \\({c}/{d}\\) on Tuesday. He ate \\({e}/{f}\\) of what he baked on Tuesday. How much cake is left in total?",
        "answerFormula": "simplifyFraction(a*d + c*(1 - e/f)*b, b*d)"
      },
      {
        "id": "ALG1-0.3-A2",
        "type": "template",
        "objective": "Multi-step Fraction Operations",
        "difficulty": "advanced",
        "variables": { "a": { "min": 1, "max": 5 }, "b": { "min": 2, "max": 12, "exclude":["a"] }, "c": { "min": 1, "max": 7 }, "d": { "min": 2, "max": 10, "exclude":["c"] }, "e": { "min": 1, "max": 4 }, "f": { "min": 2, "max": 8, "exclude":["e"] } },
        "question": "A garden uses \\({a}/{b}\\) of a bag of fertilizer in the morning and \\({c}/{d}\\) in the afternoon. If \\({e}/{f}\\) of the total used fertilizer is for vegetables, how much fertilizer was used for vegetables?",
        "answerFormula": "simplifyFraction((a/b + c/d) * e/f, 1)"
      },
      {
        "id": "ALG1-0.3-A3",
        "type": "template",
        "objective": "Multi-step Fraction Operations",
        "difficulty": "advanced",
        "variables": { "a": { "min": 1, "max": 5 }, "b": { "min": 2, "max": 12, "exclude":["a"] }, "c": { "min": 1, "max": 7 }, "d": { "min": 2, "max": 10, "exclude":["c"] }, "e": { "min": 1, "max": 4 }, "f": { "min": 2, "max": 8, "exclude":["e"] } },
        "question": "A ribbon is \\({a}/{b}\\) meters long. Sarah cuts \\({c}/{d}\\) of it and then cuts that piece into \\({e}/{f}\\) equal parts. How long, in meters, is each part?",
        "answerFormula": "simplifyFraction(a*c, b*d*e/f)"
      },
      {
        "id": "AlG1-0.4-B1",
        "type": "template",
        "objective": "Plotting points on the coordinate plane",
        "difficulty": "basic",
        "variables": {
          "a": {"min":-10, "max":10},
          "b": {"min":-10, "max":10}
        },
        "question": "Plot the point \\(({a}, {b})\\) on the coordinate plane.",
        "answer": "the x-value is \\({a}\\) while the y-value is \\({b}\\)."
      },
      {
        "id": "AlG1-0.4-B2",
        "type": "template",
        "objective": "Plotting points on the coordinate plane",
        "difficulty": "basic",
        "variables": {
          "a": {"min":-10, "max":10},
          "b": {"min":-10, "max":10},
          "c": {"min":-10, "max":10},
          "d": {"min":-10, "max":10}
        },
        "question": "Plot the points \\(({a}, {b})\\) and \\(({c}, {d})\\) on the coordinate plane.",
        "answer": "First point: x is \\({a}\\) y is \\({b}\\); Second point: x is \\({c}\\) y is \\({d}\\)."
      }

    ],
    "Module 1": [
      {
        "id": "ALG1-1.1-B1",
        "type": "template",
        "objective": "Evaluating Numerical Expressions",
        "difficulty": "basic",
        "variables": {
          "a": { "min": -20, "max": 20, "exclude":[0] },
          "b": { "min": 2, "max": 20, "exclude":["a"] },
          "c": { "min": -20, "max": 20, "exclude":["a","b",0] },
          "d": { "min": 2, "max": 20, "exclude":["a","b","c"] }
        },
        "question": "Evaluate: \\( [{a} + ({b})] \\cdot ({c}) - ({d}) \\).",
        "answerFormula": "(a + b) * c - d"
      },
      {
        "id": "ALG1-1.1-B2",
        "type": "template",
        "objective": "Evaluating Numerical Expressions",
        "difficulty": "basic",
        "variables": {
          "a": { "min": -20, "max": 20 },
          "b": { "min": 1, "max": 10 },
          "c": { "min": 1, "max": 10, "exclude":["b"] },
          "d": { "min": 2, "max": 5 },
          "e": { "min": 2, "max": 10 },
          "f": { "min": 2, "max": 20, "exclude":["d","e"] }
        },
        "question": "Evaluate: \\( {a} +({b}-{c})^2 - {d}\\cdot{e} + ({f}) \\).",
        "answerFormula": "a + (b - c) ** 2 - d * e + f"
      },
      {
        "id": "ALG1-1.1-I1",
        "type": "template",
        "objective": "Evaluating Numerical Expressions",
        "difficulty": "intermediate",
        "variables": {
          "a": { "min": -12, "max": 12, "exclude":[0] },
          "b": { "min": 1, "max": 5 },
          "c": { "min": 2, "max": 5, "exclude":["a"] },
          "d": { "min": 2, "max": 8, "exclude":[0] },
          "e": { "min":2, "max": 5, "exclude":["b","c"] },
          "f": { "min": 2, "max": 10, "exclude":["d"] }
        },
        "question": "Evaluate: \\( \\frac{{{a}}}{{{c}}} + (\\frac{{{b}}}{{{e}}})^2 - {d} + {f} \\).",
        "answerFormula": "(a/ c) + (b/e) ** 2 - d + f"
      },
      {
        "id": "ALG1-1.1-I2",
        "type": "template",
        "objective": "Evaluating Numerical Expressions",
        "difficulty": "intermediate",
        "variables": {
          "a": { "min": -7, "max": 7, "exclude":[0] },
          "b": { "min": 2, "max": 5, "exclude":["a"] },
          "c": { "min": -3, "max": 3, "exclude":[0] },
          "d": { "min": 2, "max": 5 },
          "e": { "min": 2, "max": 6 },
          "f": { "min": 2, "max": 5, "exclude":["e"]}
        },
        "question": "Evaluate: \\( \\frac{{{a}}}{{{b}}} - ({c} + \\frac{1}{{{d}}}) + \\frac{{{e}}}{{{f}}} \\).",
        "answerFormula": "(a/ b) - (c + 1/d) + (e/ f)"
      },
      {
        "id": "ALG1-1.1-A1",
        "type": "template",
        "objective": "Evaluating Numerical Expressions",
        "difficulty": "advanced",
        "variables": {
          "a": { "min": -20, "max": 20, "exclude":[0] },
          "b": { "min": 2, "max": 5, "exclude":["a"] },
          "c": { "min": 2, "max": 10, "exclude":["a","b"] },
          "d": { "min": 2, "max": 10, "exclude":["c"] },
          "e": { "min": 2, "max": 7, "exclude":["d"] },
          "f": { "min": 2, "max": 5, "exclude":["e"] },
          "g": { "min": 2, "max": 15 }
        },
        "question": "Evaluate: \\( \\frac{{{a}}}{{{b}}} + (\\frac{{{c}}}{{{d}}})^2 - \\frac{{{e}}}{{{f}}} \\cdot {g} \\).",
        "answerFormula": "(a / b) + (c / d) ** 2 - (e / f) * g"
      },
      {
        "id": "ALG1-1.1-A2",
        "type": "template",
        "objective": "Evaluating Numerical Expressions",
        "difficulty": "advanced",
        "variables": {
          "a": { "min": -12, "max": 12, "exclude":[0] },
          "b": { "min": 2, "max": 6, "exclude":["a"] },
          "c": { "min": -10, "max": 10, "exclude":[0] },
          "d": { "min": 2, "max": 8 },
          "e": { "min": 2, "max": 8, "exclude":["d"] },
          "f": { "min": 2, "max": 10 },
          "g": { "min": 2, "max": 10, "exclude":["f"] }
        },
        "question": "Evaluate: \\( \\frac{{{a}}}{{{b}}} - (\\frac{{{c}}}{{{d}}} + \\frac{1}{{{e}}}) + (\\frac{{{f}}}{{{g}}})^2 \\).",
        "answerFormula": "(a / b) - (c / d + 1 / e) + (f / g) ** 2"
      },
      {
        "id": "ALG1-1.2-B1",
        "type": "template",
        "objective": "Evaluate Algebraic Expressions",
        "difficulty": "basic",
        "variables": {
          "x": { "min": 1, "max": 5 },
          "a": { "min": 1, "max": 10 },
          "b": { "min": 1, "max": 10 }
        },
        "question": "Evaluate: \\( {a}x + {b} \\) when \\( x = {x} \\).",
        "answerFormula": "(a * x + b)"
      },
      {
        "id": "ALG1-1.2-B2",
        "type": "template",
        "objective": "Evaluate Algebraic Expressions",
        "difficulty": "basic",
        "variables": {
          "x": { "min": -7, "max": 7, "exclude": [0] },
          "a": { "min": 2, "max": 10 },
          "b": { "min": 2, "max": 10, "exclude":["a"] },
          "c": { "min": 2, "max": 10, "exclude":["a","b"] }
        },
        "question": "Evaluate: \\( {a}x^2 + {b}x + {c} \\) when \\( x = {x} \\).",
        "answerFormula": "(a * x ** 2 + b * x + c)"
      },
      {
        "id": "ALG1-1.2-I1",
        "type": "template",
        "objective": "Evaluate Algebraic Expressions",
        "difficulty": "intermediate",
        "variables": {
          "x": { "min": 1, "max": 5 },
          "y": { "min": -3, "max": 3, "exclude": [0] },
          "a": { "min": 2, "max": 10 },
          "b": { "min": 2, "max": 10 },
          "c": { "min": 2, "max": 10, "exclude":["a","b"] }
        },
        "question": "Evaluate: \\( {a}(x - {b})^2 + {c}y \\) when \\( x = {x}, y = {y} \\).",
        "answerFormula": "(a * (x - b) ** 2 + c * y)"
      },
      {
        "id": "ALG1-1.2-I2",
        "type": "template",
        "objective": "Evaluate Algebraic Expressions",
        "difficulty": "intermediate",
        "variables": {
          "x": { "min": -10, "max": 10, "exclude": [0,1] },
          "y": { "min": -5, "max": 5, "exclude": [0,1] },
          "a": { "min": 2, "max": 10, "exclude":["x"] },
          "b": { "min": 2, "max": 10 },
          "c": { "min": 2, "max": 10, "exclude":["a","b"] }
        },
        "question": "Evaluate: \\( \\frac{x - {a}}{{b}+{c}y} \\) when \\( x = {x}, y = {y} \\).",
        "answerFormula": "simplifyFraction(x - a, b + c * y)"
      },
      {
        "id": "ALG1-1.2-A1",
        "type": "template",
        "objective": "Evaluate Algebraic Expressions",
        "difficulty": "advanced",
        "variables": {
          "x": { "min": 2, "max": 5 },
          "y": { "min": -5, "max": 5, "exclude": [0] },
          "a": { "min": 2, "max": 5 },
          "b": { "min": 2, "max": 5, "exclude":["a"] },
          "c": { "min": 2, "max": 5, "exclude":["a","b"] }
        },
        "question": "Evaluate: \\( {a}x^2 + {b}xy + {c}y^2 \\) when \\( x = {x}, y = {y} \\).",
        "answerFormula": "(a * x ** 2 + b * x * y + c * y ** 2)"
      },
      {
        "id": "ALG1-1.2-A2",
        "type": "template",
        "objective": "Evaluate Algebraic Expressions",
        "difficulty": "advanced",
        "variables": {
          "x": { "min": 2, "max": 5 },
          "y": { "min": -5, "max": 5, "exclude": [0] },
          "a": { "min": 2, "max": 5 },
          "b": { "min": 2, "max": 5, "exclude":["a"] },
          "c": { "min": 2, "max": 5, "exclude":["a","b"] }
        },
        "question": "Evaluate: \\( \\frac{{a}}{ x } + \\frac{{b}}{ y } + \\frac{{{c}}}{xy} \\) when \\( x = {x}, y = {y} \\).",
        "answerFormula": "simplifyFraction(a * y + b * x + c, x * y)"
      },
      {
        "id": "ALG1-1.3-B1",
        "type": "template",
        "objective": "Evaluate Numerical Expressions by Applying Properties",
        "difficulty": "basic",
        "variables": {
          "a": { "min": 2, "max": 20 },
          "b": { "min": 2, "max": 20, "exclude":["a"] },
          "c": { "min": 2, "max": 20, "exclude":["a","b"] },
          "d": { "min": 2, "max": 20, "exclude":["a","b","c"] },
          "e": { "min": 2, "max": 20, "exclude":["a","b","c","d"] },
          "f": { "min": 2, "max": 20, "exclude":["d","e"] }
        },
        "question": "Fill in the property name used for each equation:<br><br><table border='1' style='border-collapse:collapse; text-align:center;'><tr><th>Equation</th><th>Property</th></tr><tr><td>\\(\\frac{{a}}{{b}} \\cdot \\frac{{b}}{{a}} = 1\\)</td><td>__________</td></tr><tr><td>\\( {a} + {b} = {b} + {a}\\)</td><td>__________</td></tr><tr><td>\\( ({a} + {b}) + {c} = {a} + ({b} + {c}) \\)</td><td>__________</td></tr><tr><td>\\( {a} \\cdot 1 = {a} \\)</td><td>__________</td></tr><tr><td>\\( {d} + 0 = {d} \\)</td><td>__________</td></tr><tr><td>\\( {e} + (-{e}) = 0 \\)</td><td>__________</td></tr></table>",
        "answer": "<ul> <li><strong>\\(\\frac{{a}}{{b}} \\cdot \\frac{{b}}{{a}} = 1\\)</strong>: Multiplicative Inverse Property</li>\\ <li><strong>\\({a} + {b} = {b} + {a}\\)</strong>: Commutative Property of Addition</li>\\ <li><strong>\\( ({a} + {b}) + {c} = {a} + ({b} + {c}) \\)</strong>: Associative Property of Addition</li>\\ <li><strong>\\( {a} \\cdot 1 = {a} \\)</strong>: Multiplicative Identity Property</li>\\ <li><strong>\\( {d} + 0 = {d} \\)</strong>: Additive Identity Property</li>\\ <li><strong>\\( {e} + (-{e}) = 0 \\)</strong>: Additive Inverse Property</li>\\ </ul>"
      },
      {
        "id": "ALG1-1.3-B1",
        "type": "template",
        "objective": "Evaluate Numerical Expressions by Applying Properties",
        "difficulty": "basic",
        "variables": {
          "a": { "min": 2, "max": 20 },
          "b": { "min": 2, "max": 20, "exclude":["a"] },
          "c": { "min": 2, "max": 20, "exclude":["a","b"] },
          "d": { "min": 2, "max": 20, "exclude":["a","b","c"] },
          "e": { "min": 2, "max": 20, "exclude":["a","b","c","d"] },
          "f": { "min": 2, "max": 20, "exclude":["d","e"] }
        },
        "question": "Fill in the property name used for each equation:<br><br><table border='1' style='border-collapse:collapse; text-align:center;'><tr><th>Equation</th><th>Property</th></tr><tr><td>\\({a} + {b} = {b} + {a}\\)</td><td>__________</td></tr><tr><td>\\( ({a} + {b}) + {c} = {a} + ({b} + {c}) \\)</td><td>__________</td></tr><tr><td>\\( {a} \\cdot 1 = {a} \\)</td><td>__________</td></tr><tr><td>\\( {a} \\cdot \\frac{{{b}}}{{{c}}} = \\frac{{{a} \\cdot {b}}}{{{c}}} \\)</td><td>__________</td></tr><tr><td>\\( {d} + 0 = {d} \\)</td><td>__________</td></tr><tr><td>\\( {e} + (-{e}) = 0 \\)</td><td>__________</td></tr></table>",
        "answer": "<ul> <li><strong>\\({a} + {b} = {b} + {a}\\)</strong>: Commutative Property of Addition</li>\\ <li><strong>\\( ({a} + {b}) + {c} = {a} + ({b} + {c}) \\)</strong>: Associative Property of Addition</li>\\ <li><strong>\\( {a} \\cdot 1 = {a} \\)</strong>: Multiplicative Identity Property</li>\\ <li><strong>\\( {a} \\cdot \\frac{{{b}}}{{{c}}} = \\frac{{{a} \\cdot {b}}}{{{c}}} \\)</strong>: Distributive Property</li>\\ <li><strong>\\( {d} + 0 = {d} \\)</strong>: Additive Identity Property</li>\\ <li><strong>\\( {e} + (-{e}) = 0 \\)</strong>: Additive Inverse Property</li>\\ </ul>"
      },
      {
        "id": "ALG1-1.3-I1",
        "type": "template",
        "objective": "Evaluate Numerical Expressions by Applying Properties",
        "difficulty": "intermediate",
        "variables": {
          "a": { "min": 2, "max": 20 },
          "b": { "min": 2, "max": 20, "exclude":["a"] },
          "c": { "min": 2, "max": 20, "exclude":["a","b"] },
          "d": { "min": 2, "max": 20, "exclude":["a","b","c"] },
          "e": { "min": 2, "max": 20, "exclude":["a","b","c","d"] }
        },
        "question": "Evaluate and identify the property use at each step: \\( \\bigl({d} + {a} + \\frac{{b}}{{c}}\\cdot\\frac{{c}}{{b}}\\bigr) - ({a} + {e}) \\).",
        "answer": "\\({d - e + 1}\\) <br>Properties used: Commutative Property of Addition, Multiplicative Inverse Property, Additive Inverse Property"
      },
      {
        "id": "ALG1-1.3-I2",
        "type": "template",
        "objective": "Evaluate Numerical Expressions by Applying Properties",
        "difficulty": "intermediate",
        "variables": {
          "a": { "min": 2, "max": 20 },
          "b": { "min": 2, "max": 20, "exclude":["a"] },
          "c": { "min": 2, "max": 20, "exclude":["a","b"] },
          "d": { "min": 2, "max": 20, "exclude":["a","b","c"] },
          "e": { "min": 2, "max": 20, "exclude":["a","b","c","d"] }
        },
        "question": "Evaluate and identify the property use at each step: \\( 0\\cdot({a} + {b}) + \\frac{{c}}{{d}} - \\frac{{c}}{{d}} + {e} \\).",
        "answer": "\\({e}\\) <br>Properties used: Multiplicative Property of Zero, Additive Inverse Property, Additive Identity Property"
      },
      {
        "id": "ALG1-1.4-B1",
        "type": "template",
        "objective": "Use the Distributive Property to Simplify and Evaluate Expressions",
        "difficulty": "basic",
        "variables": {
          "a": { "min": -10, "max": 10, "exclude": [0,1,-1] },
          "b": { "min": -10, "max": 10, "exclude": [0,1,-1] },
          "c": { "min": 2, "max": 10 }
        },
        "question": "Use the distributive property to simplify: \\( {a}({b}x+{c}) \\).",
        "answer": "\\({a * b}x + {a * c}\\)"
      },
      {
        "id": "ALG1-1.4-B2",
        "type": "template",
        "objective": "Use the Distributive Property to Simplify and Evaluate Expressions",
        "difficulty": "basic",
        "variables": {
          "a": { "min": 2, "max": 10, "exclude": [0,1,-1] },
          "b": { "min": -10, "max": 10, "exclude": [0,1,-1] },
          "c": { "min": 2, "max": 10 }
        },
        "question": "Use the distributive property to simplify: \\( ({b}x-{c})\\cdot{a}y \\).",
        "answer": "\\({a * b}xy + {-a * c}y\\)"
      },
      {
        "id": "ALG1-1.4-I1",
        "type": "template",
        "objective": "Use the Distributive Property to Simplify and Evaluate Expressions",
        "difficulty": "intermediate",
        "variables": {
          "a": { "min": -10, "max": 10, "exclude": [0] },
          "b": { "min": 2, "max": 10 },
          "c": { "min": -10, "max": 10, "exclude": [0] },
          "d": { "min": 3, "max": 15 },
          "e": { "min": 2, "max": 15 },
          "f": { "min": 2, "max": 15 }
        },
        "question": "Simplify by distributing and combining like terms: \\( {a}x + {b}({c}x+{d}y-{e}) - {f} \\).",
        "answer": "\\({a + b*c}x + {b*d}y + {-b*e - f}\\)"
      },
      {
        "id": "ALG1-1.4-I2",
        "type": "template",
        "objective": "Use the Distributive Property to Simplify and Evaluate Expressions",
        "difficulty": "intermediate",
        "variables": {
          "a": { "min": -10, "max": 10, "exclude": [0,1,-1] },
          "b": { "min": 2, "max": 10 },
          "c": { "min": 2, "max": 7},
          "d": { "min": -5, "max": 5, "exclude": [0] },
          "e": { "min": 2, "max": 7 },
          "f": { "min": 2, "max": 7 }
        },
        "question": "Simplify by distributing and combining like terms: \\( {a}(x+{b}) + {c}({d}x-{e}) + {f} \\).",
        "answer": "\\({a + c*d}x + {a*b - c*e + f}\\)"
      },
      {
        "id": "ALG1-1.5-B1",
        "type": "template",
        "objective": "Evaluate Absolute Value Expressions",
        "difficulty": "basic",
        "variables": {
          "a": { "min": -10, "max": 10, "exclude": [0] },
          "b": { "min": -10, "max": 10, "exclude": [0] },
          "c": { "min": -10, "max": 10, "exclude": [0] },
          "d": { "min": -10, "max": 10, "exclude": [0] }
        },
        "question": "Evaluate: \\( | {a} | - | {b} + ({c}) |\\cdot {d} \\).",
        "answerFormula": "Math.abs(a) - Math.abs(b + c) * d"
      },
      {
        "id": "ALG1-1.5-B2",
        "type": "template",
        "objective": "Evaluate Absolute Value Expressions",
        "difficulty": "basic",
        "variables": {
          "a": { "min": -10, "max": 10, "exclude": [0,1] },
          "b": { "min": 2, "max": 10, "exclude": [0,1] },
          "c": { "min": 2, "max": 10 },
          "d": { "min": 2, "max": 5, "exclude": ["c"] }
        },
        "question": "Evaluate: \\( | {a} - {b} | + \\frac{{{c}}}{{{d}}} \\).",
        "answerFormula": "Math.abs(a - b) + (c / d)"
      },
      {
        "id": "ALG1-1.5-I1",
        "type": "template",
        "objective": "Evaluate Absolute Value Expressions",
        "difficulty": "intermediate",
        "variables": {
          "a": { "min": -5, "max": 7, "exclude": [0,1,-1] },
          "x": { "min": -7, "max": 7, "exclude": [0,1,-1] },
          "c": { "min": -5, "max": 7, "exclude": [0,1,-1,"a"] },
          "y": { "min": -5, "max": 7, "exclude": [0,1,-1] },
          "z": { "min": -7, "max": 7, "exclude": [0,1,-1] },
          "f": { "min": -5, "max": 7, "exclude": [0,1,-1,"z"] }
        },
        "question": "Evaluate: \\( \\left| x - | \\frac{{a}}{{c}} - y | \\right| + \\frac{{z}}{{f}} \\), when \\(x = {x}, y = {y}\\).",
        "answerFormula": "Math.abs(x - Math.abs(a/c - y)) + (z/f)"
      },
      {
        "id": "ALG1-1.5-I2",
        "type": "template",
        "objective": "Evaluate Absolute Value Expressions",
        "difficulty": "intermediate",
        "variables": {
          "a": { "min": -5, "max": 5, "exclude": [0,1,-1] },
          "x": { "min": -5, "max": 5, "exclude": [0,1,-1] },
          "c": { "min": -5, "max": 5, "exclude": [0,1,-1] },
          "y": { "min": -5, "max": 5, "exclude": [0,1,-1,"c"] },
          "z": { "min": -5, "max": 5, "exclude": [0,1,-1] },
          "f": { "min": -5, "max": 5, "exclude": [0,1,-1,"z"] }
        },
        "question": "Evaluate: \\( \\left|{a} - x\\right| + \\left|\\frac{{c}}{ y } + \\frac{{z}}{{f}}\\right| \\), when \\(x = {x}, y = {y}\\).",
        "answerFormula": "Math.abs(a - x) + Math.abs(c/y + z/f)"
      }
    ],
    "Module 8": [
      {
        "id": "ALG1-8.1-B1",
        "type": "template",
        "objective": "Multiplication Properties of Exponents",
        "difficulty": "basic",
        "variables": {
          "a": { "min": 2, "max": 10 },
          "b": { "min": 2, "max": 5, "exclude":["a"] },
          "c": { "min": 2, "max": 5 },
          "m": { "min": -5, "max": 5, "exclude":[0,1] },
          "n": { "min": 2, "max": 5, "exclude":["m"] }
        },
        "question": "Simplify: \\( {m}x^{ {a} } \\cdot {n}x^{b} \\cdot x^{c} \\).",
        "answer": "\\({m * n}x^{ a + b + c }\\)"
      },
      {
        "id": "ALG1-8.1-I1",
        "type": "template",
        "objective": "Multiplication Properties of Exponents",
        "difficulty": "intermediate",
        "variables": {
          "a": { "min": 2, "max": 10 },
          "b": { "min": 2, "max": 5, "exclude":["a"] },
          "m": { "min": -5, "max": 5, "exclude":[0,1] },
          "n": { "min": -5, "max": 5, "exclude":[0,1,"m"] }
        },
        "question": "Calculate. Leave your answer in scientific notation: \\( ({m}\\times10^{a}) \\cdot ({n}\\times10^{b}) \\).",
        "answer": "\\({m * n}\\times10^{ a + b }\\)"
      },
      {
        "id": "ALG1-8.1-A1",
        "type": "template",
        "objective": "Multiplication Properties of Exponents",
        "difficulty": "advanced",
        "variables": {
          "a": { "min": 2, "max": 10 },
          "b": { "min": 2, "max": 5 },
          "c": { "min": 2, "max": 5 },
          "d": { "min": 2, "max": 5 },
          "e": { "min": 2, "max": 5 },
          "f": { "min": 2, "max": 3 },
          "g": { "min": 2, "max": 5 },
          "m": { "min": -3, "max": 4, "exclude":[0,1] },
          "n": { "min": -3, "max": 4, "exclude":[0,1,"m"] }
        },
        "question": "Simplify: \\( ({m}x^{ {a} }y^{b})^{c}({n}xy^{d}z^{e})^{f} \\).",
        "answer": "\\({m ** c * n ** f}x^{ a * c + f }y^{ b * c + d * f }z^{ e * f }\\)"
      },
      {
        "id": "ALG1-8.2-B1",
        "type": "template",
        "objective": "Division Properties of Exponents",
        "difficulty": "basic",
        "variables": {
          "a": { "min": 2, "max": 9 },
          "b": { "min": 2, "max": 5 },
          "c": { "min": 2, "max": 5 },
          "m": { "values": [-6,-4,-2,2,4,6] },
          "n": { "values": [-6,-4,-2,2,4,6], "exclude":["m"] } 
        },
        "question": "Simplify: \\( \\frac{{m}x^{a} \\cdot x^{b}}{{n}x^{c}} \\).",
        "answer": "\\( {m} x^{a + b - c} / {n}\\)"
      },
      {
        "id": "ALG1-8.2-I1",
        "type": "template",
        "objective": "Division Properties of Exponents",
        "difficulty": "intermediate",
        "variables": {
          "a": { "min": 2, "max": 9 },
          "b": { "min": 2, "max": 5 },
          "c": { "min": 2, "max": 3 },
          "d": { "min": 2, "max": 5, "exclude":["a"] },
          "e": { "min": 2, "max": 5, "exclude":["b"] },
          "f": { "min": 2, "max": 5, "exclude":["c"] },
          "g": { "min": 2, "max": 5 },
          "m": { "values": [-6,-4,-2,2,4,6] },
          "n": { "values": [-6,-3,3,6], "exclude":["m"] }
        },
        "question": "Simplify: \\( \\big(\\frac{{m}x^{a}y^{b}z^{c}}{{n}x^{d}y^{e}z^{f}}\\big)^{g} \\).",
        "answer": "\\( {(m/n) ** g} x^{(a - d) * g} y^{ (b - e) * g } z^{ (c - f) * g } \\)"
      },
      {
        "id": "ALG1-8.3-B1",
        "type": "template",
        "objective": "Negative Exponents",
        "difficulty": "basic",
        "variables": {
          "a": { "min": 2, "max": 10 },
          "b": { "min": 2, "max": 5, "exclude":["a"] },
          "c": { "min": 2, "max": 5, "exclude":["a","b"] }
        },
        "question": "",
        "answer": ""
      },
      {
        "id": "ALG1-8.3-I1",
        "type": "template",
        "objective": "Negative Exponents",
        "difficulty": "intermediate",
        "variables": {
          "a": { "min": 2, "max": 10 },
          "b": { "min": 2, "max": 5, "exclude":["a"] },
          "c": { "min": 2, "max": 5, "exclude":["a","b"] }
        },
        "question": "",
        "answer": ""
      },
      {
        "id": "ALG1-8.4-B1",
        "type": "template",
        "objective": "Rational Exponents",
        "difficulty": "basic",
        "variables": {
          "a": { "min": 2, "max": 10 },
          "b": { "min": 2, "max": 5, "exclude":["a"] },
          "c": { "min": 2, "max": 5, "exclude":["a","b"] }
        },
        "question": "",
        "answer": ""
      },
      {
        "id": "ALG1-8.4-I1",
        "type": "template",
        "objective": "Rational Exponents",
        "difficulty": "intermediate",
        "variables": {
          "a": { "min": 2, "max": 10 },
          "b": { "min": 2, "max": 5, "exclude":["a"] },
          "c": { "min": 2, "max": 5, "exclude":["a","b"] }
        },
        "question": "",
        "answer": ""
      },
      {
        "id": "ALG1-8.5-B1",
        "type": "template",
        "objective": "Simplifying Radical Expressions",
        "difficulty": "basic",
        "variables": {
          "a": { "min": 2, "max": 10 },
          "b": { "min": 2, "max": 5, "exclude":["a"] },
          "c": { "min": 2, "max": 5, "exclude":["a","b"] }
        },
        "question": "",
        "answer": ""
      },
      {
        "id": "ALG1-8.5-I1",
        "type": "template",
        "objective": "Simplifying Radical Expressions",
        "difficulty": "intermediate",
        "variables": {
          "a": { "min": 2, "max": 10 },
          "b": { "min": 2, "max": 5, "exclude":["a"] },
          "c": { "min": 2, "max": 5, "exclude":["a","b"] }
        },
        "question": "",
        "answer": ""
      },
      {
        "id": "ALG1-8.5-A1",
        "type": "template",
        "objective": "Simplifying Radical Expressions",
        "difficulty": "advanced",
        "variables": {
          "a": { "min": 2, "max": 10 },
          "b": { "min": 2, "max": 5, "exclude":["a"] },
          "c": { "min": 2, "max": 5, "exclude":["a","b"] }
        },
        "question": "",
        "answer": ""
      },
      {
        "id": "ALG1-8.6-B1",
        "type": "template",
        "objective": "Operations with Radical Expressions",
        "difficulty": "basic",
        "variables": {
          "a": { "min": 2, "max": 10 },
          "b": { "min": 2, "max": 5, "exclude":["a"] },
          "c": { "min": 2, "max": 5, "exclude":["a","b"] }
        },
        "question": "",
        "answer": ""
      },
      {
        "id": "ALG1-8.6-I1",
        "type": "template",
        "objective": "Operations with Radical Expressions",
        "difficulty": "intermediate",
        "variables": {
          "a": { "min": 2, "max": 10 },
          "b": { "min": 2, "max": 5, "exclude":["a"] },
          "c": { "min": 2, "max": 5, "exclude":["a","b"] }
        },
        "question": "",
        "answer": ""
      },
      {
        "id": "ALG1-8.6-A1",
        "type": "template",
        "objective": "Operations with Radical Expressions",
        "difficulty": "advanced",
        "variables": {
          "a": { "min": 2, "max": 10 },
          "b": { "min": 2, "max": 5, "exclude":["a"] },
          "c": { "min": 2, "max": 5, "exclude":["a","b"] }
        },
        "question": "",
        "answer": ""
      }
    ],
    "Module 2": [
      {
        "id": "ALG1-2.1-I1",
        "type": "template",
        "objective": "Solving One-Step Equations",
        "difficulty": "intermediate",
        "variables": {
          "a": { "min": 1, "max": 10 },
          "b": { "min": 1, "max": 10 }
        },
        "question": "Solve for x: \\( x + {a} = {b} \\).",
        "answer": "\\( x = {b} - {a} = {b - a} \\)"
      },
      {
        "id": "ALG1-2.1-I2",
        "type": "template",
        "objective": "Solving One-Step Equations",
        "difficulty": "intermediate",
        "variables": {
          "a": { "min": 1, "max": 10 },
          "b": { "min": 10, "max": 20 }
        },
        "question": "Solve for x: \\( x - {a} = {b} \\).",
        "answer": "\\( x = {b} + {a} = {b + a} \\)"
      },
      {
        "id": "ALG1-2.1-I3",
        "type": "template",
        "objective": "Solving One-Step Equations",
        "difficulty": "intermediate",
        "variables": {
          "a": { "min": 2, "max": 10 },
          "b": { "min": 10, "max": 50 }
        },
        "question": "Solve for x: \\( {a}x = {b} \\).",
        "answer": "\\( x = \\frac{{{b}}}{{{a}}} = {(b / a).toFixed(2)} \\)"
      },
      {
        "id": "ALG1-2.1-I4",
        "type": "template",
        "objective": "Solving One-Step Equations",
        "difficulty": "intermediate",
        "variables": {
          "a": { "min": 2, "max": 10 },
          "b": { "min": 10, "max": 50 }
        },
        "question": "Solve for x: \\( \\frac{x}{ {a} } = {b} \\).",
        "answer": "\\( x = {a} \\times {b} = {a * b} \\)"
      } 
    ],
    "Template": [
      {
        "id": "A1-1.1-B1",
        "type": "template",
        "objective": "Find intercepts of linear equations",
        "difficulty": "basic",
        "variables": {
          "m": { "min": -5, "max": 5, "exclude": [0] },
          "b": { "min": -10, "max": 10 }
        },
        "question": "Find the x- and y-intercepts of \\( y = {m}x + {b} \\).",
        "answer": "x-intercept: \\(\\left(-\\frac{{b}}{{m}}, 0\\right)\\), y-intercept: (0, {b})"
      },
      {
        "id": "A1-1.1-B1",
        "type": "template",
        "objective": "Find intercepts of linear equations",
        "difficulty": "basic",
        "variables": {
          "m": { "min": -5, "max": 5, "exclude": [0] },
          "b": { "min": -10, "max": 10 }
        },
        "question": "Find the x- and y-intercepts of \\( y = {m}x + {b} \\).",
        "draw": "linearGraph",
        "answer": "x-intercept: \\(\\left(-\\frac{{b}}{{m}}, 0\\right)\\), y-intercept: (0, {b})"
      }
    ]
  },

  "Geometry": {
    "Chapter 1": [
      {
        "id": "Geo-1.2-B1",
        "type": "template",
        "objective": "Identify points, lines, line segments, rays, and planes",
        "difficulty": "basic",
        "variables": {},
        "question": "Currently unavailable.",
        "answer": "Answer currently unavailable."
      },
      {
        "id": "Geo-1.3a-B1",
        "type": "template",
        "objective": "Calculate measures of line segments",
        "difficulty": "basic",
        "variables": {},
        "question": "Currently unavailable.",
        "answer": "Answer currently unavailable."
      },
      {
        "id": "Geo-1.3b-B1",
        "type": "template",
        "objective": "Apply the definition of congruent lines segments",
        "difficulty": "basic",
        "variables": {},
        "question": "Currently unavailable.",
        "answer": "Answer currently unavailable."
      },
      {
        "id": "Geo-1.4-B1",
        "type": "template",
        "objective": "Find the distance between two points",
        "difficulty": "basic",
        "variables": { 
          "x1": { "min": -20, "max": 20 },
          "x2": { "min": -20, "max": 20, "exclude": ["x1"] }
        },
        "question": "Find the distance between \\( {x1} \\) and \\( {x2} \\) on a number line.",
        "answer": "Distance = \\( |{x2 - x1}| \\)"
      },
      {
        "id": "Geo-1.4-I1",
        "type": "template",
        "objective": "Find the distance between two points",
        "difficulty": "intermediate",
        "variables": {
          "x1": { "min": -6, "max": 6 },
          "y1": { "min": -6, "max": 6 },
          "x2": { "min": -6, "max": 6, "exclude": ["x1"] },
          "y2": { "min": -6, "max": 6, "exclude": ["y1"] }
        },
        "question": "Find the distance between points \\(({x1}, {y1})\\) and \\(({x2}, {y2})\\). Round your answer to the nearest hundredth.",
        "answerFormula": "calculateDistance(x1, y1, x2, y2)"
      },
      {
        "id": "Geo-1.4-A1",
        "type": "template",
        "objective": "Find the distance between two points",
        "difficulty": "Advanced",
        "variables": {
          "x1": { "min": -10, "max": 10 },
          "y1": { "min": -10, "max": 10 },
          "x2": { "min": -10, "max": 10, "exclude": ["x1"] },
          "y2": { "min": -10, "max": 10, "exclude": ["y1"] }
        },
        "question": "Find the distance between points \\(({x1}, {y1})\\) and \\(({x2}, {y2})\\). Express your answer in simplified radical form.",
        "answerFormula": "calculateDistance(x1, y1, x2, y2)"
      },
      {
        "id": "Geo-1.5a-B1",
        "type": "template",
        "objective": "Find a point on a line that is a fractional distance from an endpoint",
        "difficulty": "basic",
        "variables": { 
          "x1": { "min": -20, "max": 20 },
          "x2": { "min": -20, "max": 20, "exclude": ["x1"] },
          "a": { "min":2, "max":5 },
          "b": { "min":3, "max":10, "exclude":["a"] }
        },
        "question": "Find the point that is \\( \\frac{{{a}}}{{{b}}} \\) of the way from \\( {x1} \\) to \\( {x2} \\).",
        "answer": "Point = \\( {x1 + (a/b)*(x2 - x1)} \\)"
      },
      {
        "id": "Geo-1.5b-B2",
        "type": "template",
        "objective": "Find a point that partitions a line by a given ratio",
        "difficulty": "basic",
        "variables": { 
          "x1": { "min": -20, "max": 20 },
          "x2": { "min": -20, "max": 20, "exclude": ["x1"] },
          "a": { "min":2, "max":5 },
          "b": { "min":3, "max":10, "exclude":["a"] }
        },
        "question": "Find the point that partitions the line segment from \\( {x1} \\) to \\( {x2} \\) in the ratio \\( {a}:{b} \\).",
        "answer": "Point = \\( {(a*x2 + b*x1)/(a + b)} \\)"
      },
      {
        "id": "Geo-1.6a-B1",
        "type": "template",
        "objective": "Find a point on a line in two dimentions that is a fractitonal distance from an endpoint",
        "difficulty": "basic",
        "variables": { 
          "x1": { "min": -10, "max": 10 },
          "y1": { "min": -10, "max": 10 },
          "x2": { "min": -10, "max": 10, "exclude": ["x1"] },
          "y2": { "min": -10, "max": 10, "exclude": ["y1"] },
          "a": { "min":2, "max":5 },
          "b": { "min":3, "max":10, "exclude":["a"] }
        },
        "question": "Find the point that is \\( \\frac{{{a}}}{{{b}}} \\) of the way from \\( ({x1}, {y1}) \\) to \\( ({x2}, {y2}) \\).",
        "answer": "Point = \\( ({x1 + (a/b)*(x2 - x1)}, {y1 + (a/b)*(y2 - y1)}) \\)"
      },
      {
        "id": "Geo-1.6b-B2",
        "type": "template",
        "objective": "Find a point that partitions a line in two dimensions by a given ratio",
        "difficulty": "basic",
        "variables": { 
          "x1": { "min": -10, "max": 10 },
          "y1": { "min": -10, "max": 10 },
          "x2": { "min": -10, "max": 10, "exclude": ["x1"] },
          "y2": { "min": -10, "max": 10, "exclude": ["y1"] },
          "a": { "min":2, "max":5 },
          "b": { "min":3, "max":10, "exclude":["a"] }
        },
        "question": "Find the point that partitions the line segment from \\( ({x1}, {y1}) \\) to \\( ({x2}, {y2}) \\) in the ratio \\( {a}:{b} \\).",
        "answer": "Point = \\( ({(a*x2 + b*x1)/(a + b)}, {(a*y2 + b*y1)/(a + b)}) \\)"
      },
      {
        "id": "Geo-1.7-B1",
        "type": "template",
        "objective": "Find the coordinate of a midpoint",
        "difficulty": "basic",
        "variables": { 
          "x1": { "min": -10, "max": 10 },
          "x2": { "min": -10, "max": 10, "exclude": ["x1"] }
        },
        "question": "Find the midpoint of the line segment from \\( {x1} \\) to \\( {x2} \\).",
        "answer": "Midpoint = \\( {(x1 + x2)/2} \\)"      
      },
      {
        "id": "Geo-1.7-I1",
        "type": "template",
        "objective": "Find the coordinate of a midpoint",
        "difficulty": "intermediate",
        "variables": { 
          "x1": { "min": -10, "max": 10 },
          "y1": { "min": -10, "max": 10 },
          "x2": { "min": -10, "max": 10, "exclude": ["x1"] },
          "y2": { "min": -10, "max": 10, "exclude": ["y1"] }
        },
        "question": "Find the midpoint of the line segment from \\( ({x1}, {y1}) \\) to \\( ({x2}, {y2}) \\).",
        "answer": "Midpoint = \\( ({(x1 + x2)/2}, {(y1 + y2)/2}) \\)"
      },
      {
        "id": "Geo-1.7-A1",
        "type": "template",
        "objective": "Find the coordinate of a midpoint",
        "difficulty": "advanced",
        "variables": { 
          "x1": { "min": -10, "max": 10 },
          "y1": { "min": -10, "max": 10 },
          "x2": { "min": -10, "max": 10, "exclude": ["x1"] },
          "y2": { "min": -10, "max": 10, "exclude": ["y1"] }
        },
        "question": "Find the coordinates of points B given that M is the midpoint of line segment AB and M = \\( ({x1}, {y1}) \\) and A = \\( ({x2}, {y2}) \\).",
        "answer": "B = \\( ({2*x1 - x2}, {2*y1 - y2}) \\)"
      }
    ],
    "Chapter 2": [
      {"id": "G-2.1-B1",
        "type": "template",
        "objective": "Find the hypotenuse of a right triangle",
        "difficulty": "basic",
        "variables": {
          "a": { "min": 3, "max": 8 },
          "b": { "min": 3, "max": 8 }
        },
        "question": "Find the hypotenuse of a right triangle with legs {a} and {b}.",
        "draw": "rightTriangle",
        "answer": "Hypotenuse = \\( \\sqrt{{a}^2 + {b}^2} = {(Math.sqrt(a*a + b*b)).toFixed(2)} \\)"
      },
      {
        "id": "G-2.1-B1",
        "type": "template",
        "objective": "Find the area of a triangle",
        "difficulty": "basic",
        "variables": {
          "base": { "min": 3, "max": 10 },
          "height": { "min": 3, "max": 10 }
        },
        "question": "Find the area of a triangle with base {base} cm and height {height} cm.",
        "answer": "Area = \\( \\frac{1}{2}({base})({height}) = {0.5*base*height} \\text{ cm}^2 \\)"
      }
    ],
    "Chapter 3": [
      {
        "id": "G-3.1-I1",
        "type": "template",
        "objective": "Calculate distance between two points",
        "difficulty": "intermediate",
        "variables": {
          "x1": { "min": -10, "max": 10 },
          "y1": { "min": -10, "max": 10 },
          "x2": { "min": -10, "max": 10 },
          "y2": { "min": -10, "max": 10 }
        },
        "question": "Find the distance between the points \\( ({x1}, {y1}) \\) and \\( ({x2}, {y2}) \\).",
        "answer": "Distance = \\( \\sqrt{{(x2 - x1)}^2 + {(y2 - y1)}^2} = {(Math.sqrt((x2 - x1)**2 + (y2 - y1)**2)).toFixed(2)} \\)"
      },
      {
        "id": "G-2.3-I1",
        "type": "template",
        "objective": "Find chord length given radius and distance from center",
        "difficulty": "intermediate",
        "question": "A circle has radius {r} and a chord {d} units from the center. Find the length of the chord.",
        "answer": "Chord length = 2 * sqrt({r}^2 - {d}^2)",
        "variables": {
          "r": { "min": 5, "max": 10 },
          "d": { "min": 1, "max": 4 }
        },
        "draw": "circleChord"
      }
    ]
  },

  "Algebra 2": {
    "Chapter 1": [
      {
        "id": "ALG2-1.1a-B1",
        "type": "template",
        "objective": "Identify Domain and Range of Functions",
        "difficulty": "basic",
        "variables": {
          "a": { "min": -3, "max": 3, "exclude": [0,1] },
          "b": {"values":[0]},
          "c": { "min": 1, "max": 5, "exclude": ["a"] }
        },
        "question": "Find the domain and range of the function \\( f(x) = {a}x^2 - {b} \\).",
        "draw": "parabola",
        "answer": "Domain: all real numbers; Range: \\( y \\geq {-b} \\) if \\( {a} > 0 \\), \\( y \\leq {-b} \\) if \\( {a} < 0 \\)."
      },
      {
        "id": "ALG2-1.1a-I2",
        "type": "template",
        "objective": "Identify Domain and Range of Functions",
        "difficulty": "intermediate",
        "variables": {
          "a": { "min":  -0.5, "max": 0.5, "exclude": [0] },
          "h": { "min": 1, "max": 3 },
          "k": { "min": 1, "max": 3 },
          "xMin": { "min": -3, "max": -1 },
          "xMax": { "min": 1, "max": 3 }
        },
        "question": "Find the domain and range of the function \\( f(x) = {a}(x - {h})^2 + {k} \\).",
        "draw": "parabola",
        "answer": "Domain: all real numbers; Range: \\( y \\geq {k} \\) if \\( {a} > 0 \\), \\( y \\leq {k} \\) if \\( {a} < 0 \\)."
      },
      {
        "id": "ALG2-1.1a-A1",
        "type": "template",
        "objective": "Identify Domain and Range of Functions",
        "difficulty": "advanced",
        "variables": {
          "a": { "min": -3, "max": 3, "exclude": [0,1] },
          "b": { "min": -5, "max": 5 },
          "c": { "min": 1, "max": 5, "exclude": ["a"] }
        },
        "question": "Find the domain and range of the piecewise function: <br> \\( f(x) = \\begin{cases} {a}x^2 + {b}, & x < 0 \\\\ \\sqrt{x + {c}}, & x \\geq 0 \\end{cases} \\).",
        "answer": "Domain: \\( x \\geq -{c} \\); Range: \\( y \\geq {b} \\) if \\( {a} > 0 \\), \\( y \\leq {b} \\) if \\( {a} < 0 \\)."
      },
      {
        "id": "ALG2-1.2a-B1",
        "type": "linearGraph",
        "objective": "Identify Intercepts of Graphs of Functions",
        "difficulty": "basic",
        "variables": {
          "m": { "min": -3, "max": 3, "exclude": [0] },
          "b": { "min": -6, "max": 6, "exclude":[0] }
        },
        "question": "Find the \\(x\\)-intercept and the \\(y\\)-intercept of the line \\(y = {m}x + {b}\\).",
        "answerFormula": "`{ xIntercept: -b/m, yIntercept: b }`",
        "draw": "linearGraph"
      },
      {
        "id": "ALG2-1.2a-B2",
        "type": "quadraticGraph",
        "objective": "Identify Intercepts of Graphs of Functions",
        "difficulty": "basic",
        "variables": {
          "r1": { "min": -4, "max": 4, "exclude": [0] },
          "r2": { "min": -4, "max": 4, "exclude": ["r1", 0] },
          "a":  { "values": [1, -1] }
        },
        "question": "Use the graph to find the \\(x\\)- and \\(y\\)-intercepts of the function.",
        "answerFormula": "({ xIntercepts: [r1, r2], yIntercept: a*r1*r2 })",
        "draw": "parabola",
        "coefficients": {
          "a": "{a}",
          "b": "{-a*(r1 + r2)}",
          "c": "{a*r1*r2}"
        }
      },

      {
        "id": "ALG2-1.2a-I1",
        "type": "linearGraph",
        "objective": "Identify Intercepts of Graphs of Functions",
        "difficulty": "intermediate",
        "variables": {
          "a": { "min": -3, "max": 6, "exclude": [0] },
          "b": { "min": 2, "max": 10, "exclude": [0, "a"] },
          "c": { "min": -10, "max": 10, "exclude": [0] }
        },
        "question": "Find the \\(x\\)-intercept and the \\(y\\)-intercept of the line \\(y = \\frac{{a}}{{b}}x + {c}\\).",
        "answerFormula": "({ xIntercept: -(c * b) / a, yIntercept: c })",
        "draw": "linearGraph"
      },

      {
        "id": "ALG2-1.2a-I2",
        "type": "linearGraph",
        "objective": "Identify Intercepts of Graphs of Functions",
        "difficulty": "intermediate",
        "variables": {
          "a": { "min":-10, "max":10, "exclude":[0]},
          "b": { "min": -5, "max": 5, "exclude":[0] },
          "c": { "min": 2, "max": 8, "exclude":["b",0] },
          "d": { "min": -10, "max": 10, "exclude":[0]}
        },
        "question": "Find the \\(x\\)-intercept and the \\(y\\)-intercept of the line \\(y-{a} = \frac{b}{c}(x - {d})\\).",
        "answer": "`{ xIntercept: d - c*a/b, yIntercept: a + b*d/c }`"
    
      },
      {
        "id": "ALG2-1.2b-B1",
        "type": "template",
        "objective": "Identify Linear and Nonlinear Functions",
        "difficulty": "basic",
        "variables": {},
        "question": "For each equation below, determine whether it is linear: <br> \\(y = -5x + 7\\), \\(y = -6\\), \\(y = x\\), \\(y = 2x^2 + 5\\).",
        "answer": "Only \\(y = 2x^2 + 5\\) is not linear."
      },
      {
        "id": "ALG2-1.2b-B2",
        "type": "template",
        "objective": "Identify Linear and Nonlinear Functions",
        "difficulty": "basic",
        "variables": {},
        "question": "For each equation below, determine whether it is linear: <br> \\(x + 6y = 5\\), \\(y = 7x + 6xy\\), \\(-\\frac{6}{x} = 5y - 4\\), \\(3x - y = 2\\).",
        "answer": "Equations 2 and 3 are not linear; equations 1 and 4 are linear."
      },
      {
        "id": "ALG2-1.2b-I1",
        "type": "template",
        "objective": "Identify Linear and Nonlinear Functions",
        "difficulty": "intermediate",
        "variables": {},
        "question": "For each equation below, determine whether it is linear: <br> \\(y = 4x - 7\\), \\(y = 3x^2 + 5\\), \\(y = -2x + 4\\), \\(y = \\frac{1}{x} + 6\\).",
        "answer": "Only \\(y = 3x^2 + 5\\) and \\(y = \\frac{1}{x} + 6\\) are not linear."
      },
      {
        "id": "ALG2-1.2b-I2",
        "type": "template",
        "objective": "Identify Linear and Nonlinear Functions",
        "difficulty": "intermediate",
        "variables": {},
        "question": "For each equation below, determine whether it is linear: <br> \\(2x + 3y = 6\\), \\(xy + 4y = 5\\), \\(\\frac{3}{x} + y = 7\\), \\(5x - y = 10\\).",
        "answer": "Equations 2 and 3 are not linear; equations 1 and 4 are linear."
      },
      {
        "id": "ALG2-1.2c-B1",
        "type": "template",
        "objective": "Identify symmetry from equations",
        "difficulty": "basic",
        "variables": {},
        "question": "For each equation below, select all symmetries that apply (\\(x\\)-axis, \\(y\\)-axis, origin, none): <br> \\(y = x^2 - 4\\), \\(y = x^3 - x\\), \\(y = x^2 + x - 6\\), \\(y = x^3 + x^2 - x - 1\\).",
        "answer": "\\(y = x^2 - 4\\) is symmetric about the y-axis; \\(y = x^3 - x\\) is symmetric about the origin; the other two have."
      },
      {
        "id": "ALG2-1.2c-I1",
        "type": "template",
        "objective": "Identify symmetry from equations",
        "difficulty": "intermediate",
        "variables": {},
        "question": "For each equation below, select all symmetries that apply (\\(x\\)-axis, \\(y\\)-axis, origin, none): <br> \\(y = x^2 - 3\\), \\(y = x^3 + x\\), \\(y = x^2 + 2x + 1\\), \\(y = x^3 - x^2 + x - 1\\).",
        "answer": "\\(y = x^2 - 3\\) is symmetric about the y-axis; \\(y = x^3 + x\\) is symmetric about the origin; the other two have no symmetry."
      },
      {
        "id": "ALG2-1.3a-B1",
        "type": "template",
        "objective": "Identify End Behavior of Graphs of Functions",
        "difficulty": "basic",
        "variables": {
          "a": { "values": [1, -1, 2, -2] },
          "b": { "min": -3, "max": 3, "exclude":[0] }
        },
        "question": "Describe the end behavior of the function \\( y = {a}x^2 + {b}x \\) as \\( x \\) approaches \\( \\infty \\) and \\( -\\infty \\).",
        "answer": "As \\( x \\to \\infty, y \\to {a > 0 ? '\\infty' : '-\\infty'} \\); as \\( x \\to -\\infty, y \\to {a > 0 ? '\\infty' : '-\\infty'} \\)."
      },
      {
        "id": "ALG2-1.3a-I1",
        "type": "template",
        "objective": "Identify End Behavior of Graphs of Functions",
        "difficulty": "intermediate",
        "variables": {
          "a": { "values": [1, -1, 2, -2] },
          "b": { "min": -3, "max": 3, "exclude":[0] },
          "c": { "min": -2, "max": 2, "exclude":[0] }
        },
        "question": "Describe the end behavior of the function \\( y = {a}x^3 + {b}x^2 + {c}x \\) as \\( x \\) approaches \\( \\infty \\) and \\( -\\infty \\).",
        "answer": "As \\( x \\to \\infty, y \\to {a > 0 ? '\\infty' : '-\\infty'} \\); as \\( x \\to -\\infty, y \\to {a > 0 ? '-\\infty' : '\\infty'} \\)."
      },
      {
        "id": "ALG2-1.3b-B1",
        "type": "template",
        "objective": "Identify Extrema of Graphs and Functions",
        "difficulty": "basic",
        "variables": {
          "a": { "values": [1, -1, 2, -2] },
          "b": { "min": -3, "max": 3, "exclude":[0] },
          "c": { "min": -2, "max": 2, "exclude":[0] }
        },
        "question": "Find the coordinates of any extrema for the function \\( y = {a}x^2 + {b}x + {c} \\).",
        "answer": "Vertex at \\( \\left( {-b/(2*a)}, {a*(-b/(2*a))**2 + b*(-b/(2*a)) + c} \\right) \\)."
      },
      {
        "id": "ALG2-1.3b-I1",
        "type": "template",
        "objective": "Identify Extrema of Graphs and Functions",
        "difficulty": "intermediate",
        "variables": {
          "a": { "values": [1, -1, 2, -2] },
          "b": { "min": -3, "max": 3, "exclude":[0] },
          "c": { "min": -2, "max": 2, "exclude":[0] },
          "d": { "min": -1, "max": 1, "exclude":[0] }
        },
        "question": "Find the coordinates of any extrema for the function \\( y = {a}x^3 + {b}x^2 + {c}x + {d} \\).",
        "answer": "Use graphing calculator to evaluate the extrema."
      }
    ],
    "Chapter 4": [
      {
        "id": "A2-Q1-B1",
        "type": "template",
        "objective": "Graph quadratic function",
        "difficulty": "basic",
        "question": "Graph the quadratic function y = {a}x + {b}x + {c}",
        "answer": "parabola",
        "variables": {
          "a": { "values": [1, -1, 2] },
          "b": { "min": -3, "max": 3, "exclude": [0] },
          "c": { "min": -2, "max": 2, "exclude": [0] }
        },
        "draw": "parabola"}
    ]
  },

  "Precalculus": {
      "Chapter 1": [
        {
          "id": "PC-1.1a-B1",
          "type": "template", 
          "objective": "To utilize multiple representations of relations and functions",
          "difficulty": "basic",
          "variables": {
            "a": { "min": -5, "max": 5, "exclude": [0] },
            "b": { "min": 2, "max": 7 },
            "c": { "min": 1, "max": 10}
          },
          "question": "Represent the function as a set of ordered pairs, a mapping diagram, and a graph: \\( f(x) = {a}x^2 - {b}x + {c} \\) for \\( x = -2, -1, 0, 1, 2 \\).",
          "answerFormula": "Answer currently unavailable."
        },
        {
          "id": "PC-1.1a-I1",
          "type": "template", 
          "objective": "To utilize multiple representations of relations and functions",
          "difficulty": "intermediate",
          "variables": {
            "a": { "min": -5, "max": 5, "exclude": [0] },
            "b": { "min": 2, "max": 7, "exclude": [0] },
            "c": { "min": 2, "max": 7, "exclude": [0] },
            "d": { "min": 1, "max": 10, "exclude": [0] }
          },
          "question": "Represent the function as a set of ordered pairs, a mapping diagram, and a graph: \\( f(x) = {a}x^3 - {b}x^2 - {c}x + {d}\\) for \\( x = -3, -2, -1, 0, 1, 2, 3 \\).",
          "answerFormula": "Answer currently unavailable."
        },
        {
          "id": "PC-1.1b-B1",
          "type": "template",
          "objective": "To identify relations that are functions",
          "difficulty": "basic",
          "variables": {
            "a": { "min": -5, "max": 5, "exclude": [0] },
            "b": { "min": 2, "max": 7 },
            "c": { "min": 1, "max": 10 }
          },
          "question": "Determine whether each expression is a function or not.<br>\\( f(x) = {a}x + {b} \\)<br>\\( {c}xy^2 = {b}y \\)<br>\\( y = \\pm\\sqrt{x - {c}} \\)<br>\\( y = \\frac{x^2 - {b}}{x - {a}} \\)",
          "answer": "Only \\( f(x) = {a}x + {b} \\) is a function."
        },
        {
          "id": "PC-1.1b-B2",
          "type": "template",
          "objective": "To identify relations that are functions",
          "difficulty": "basic",
          "variables": {
            "a": { "min": -5, "max": 5, "exclude": [0] },
            "b": { "min": 2, "max": 7 },
            "c": { "min": 1, "max": 10 }
          },
          "question": "Determine whether each expression is a function or not.<br>\\( f(x) = {a}x^2 + {b}x + {c} \\)<br>\\( {c}x^2 + {b}y^2 = {a} \\)<br>\\( y = \\sqrt{x + {c}} \\)<br>\\( y = \\frac{x - {b}}{x^2 - {a}} \\)",
          "answer": "Only \\( f(x) = {a}x^2 + {b}x + {c} \\) and \\( y = \\sqrt{x + {c}} \\) are functions."
        },
        {
          "id": "PC-1.1c-B1",
          "type": "template", 
          "objective": "To use interval notation to state the domain and range of a function",
          "difficulty": "basic",
          "variables": {
            "a": { "min": -5, "max": 5, "exclude": [0,1,-1] },
            "b": { "min": 2, "max": 7 },
            "c": { "min": 1, "max": 10}
          },
          "question": "Find the domain and range of the function \\( f(x) = {a}x^2 - {b}x + {c} \\).",
          "answer": "Domain: \\( (-\\infty, \\infty) \\); Range: \\( [{c - b^2/(4*a)}, \\infty) \\) if \\( a > 0 \\) or \\( (-\\infty, {c - b^2/(4*a)}] \\) if \\( a < 0 \\)."
        },
        {
          "id": "PC-1.1c-B2",
          "type": "template", 
          "objective": "To use interval notation to state the domain and range of a function",
          "difficulty": "basic",
          "variables": {
            "a": { "min": -5, "max": 5, "exclude": [0,1,-1] },
            "b": { "min": 2, "max": 7, "exclude": [0] },
            "c": { "min": 2, "max": 7, "exclude": [0] }
                    },
          "question": "Find the domain and range of the function \\( f(x) = {a}(x- {b})^2 + {c} \\).",
          "answer": "Domain: \\( (-\\infty, \\infty) \\); Range: \\( [{c}, \\infty) \\) if \\( a > 0 \\) or \\( (-\\infty, {c}] \\) if \\( a < 0 \\)."
        },
        {
          "id": "PC-1.1c-I1",
          "type": "template", 
          "objective": "To use interval notation to state the domain and range of a function",
          "difficulty": "intermediate",
          "variables": {
            "a": { "min": -5, "max": 5, "exclude": [0] },
            "b": { "min": 2, "max": 7, "exclude": [0] },
            "c": { "min": 2, "max": 7, "exclude": [0] },
            "d": { "min": 1, "max": 10}
          },
          "question": "Find the domain and range of the function \\( f(x) = {a}\\bigl(\\frac{{b}}{x-{c}}\\bigr) + {d} \\).",
          "answer": "Domain: \\( (-\\infty, {c}) \\cup ({c}, \\infty) \\); Range: \\( (-\\infty, {d}) \\cup ({d}, \\infty) \\) if \\( a > 0 \\) or \\( (-\\infty, {d}) \\cup ({d}, \\infty) \\) if \\( a < 0 \\)."
        },
        {
          "id": "PC-1.1c-I2",
          "type": "template", 
          "objective": "To use interval notation to state the domain and range of a function",
          "difficulty": "intermediate",
          "variables": {
            "a": { "min": -5, "max": 5, "exclude": [0,1,-1] },
            "b": { "min": 2, "max": 7, "exclude": [0] },
            "c": { "min": 2, "max": 7, "exclude": [0] }
          },
          "question": "Find the domain and range of the function \\( f(x) = {a}\\sqrt{x - {b}} + {c} \\).",
          "answer": "Domain: \\( [{b}, \\infty) \\); Range: \\( [{c}, \\infty) \\) if \\( a > 0 \\) or \\( (-\\infty, {c}] \\) if \\( a < 0 \\)."
        },
        {
          "id": "PC-1.2a-B1",
          "type": "linearGraph",
          "objective": "Graph linear equations",
          "difficulty": "basic",
          "variables": {
            "a": { "min": -3, "max": 3, "exclude": [0] },
            "b": { "min": -5, "max": 5, "exclude": [0, "a"] },
            "c": { "min": 1, "max": 6 }
          },
          "question": "Graph the line \\(y = \\frac{{a}}{{b}}x + {c}\\) on the coordinate plane.",
          "answer": "Linear graph with slope \\(\\frac{a}{b}\\) and y-intercept \\({c}\\)."        
        },
        {
          "id": "PC-1.2b-B1",
          "type": "linearGraph",
          "objective": "Find intercepts",
          "difficulty": "basic",
          "variables": {
            "a": { "min": -4, "max": 4, "exclude": [0] },
            "b": { "min": 2, "max": 6, "exclude": ["a"] },
            "c": { "min": -10, "max": 10 }
          },
          "question": "Find the \\(x\\)- and \\(y\\)-intercepts of the line \\({a}x - {b}y = {c}\\).",
          "answerFormula": "`{ xIntercept: c/a, yIntercept: -c/b }`"
        },
        {
          "id": "PC-1.2c-B1",
          "type": "template",
          "objective": "Write an equation of a given line",
          "difficulty": "basic",
          "variables": {
            "x1": { "min": -6, "max": 6 },
            "y1": { "min": -6, "max": 6 },
            "a": { "min": -4, "max": 4, "exclude": [0] },
            "b": { "min": 2, "max": 10, "exclude": [0, "a"] }
          },
          "question": "Write the equation of the line with slope \\(m = \\frac{{a}}{{b}}\\) passing through \\(({x1}, {y1})\\) in two forms: point-slope and slope-intercept.",
          "answerFormula": "`let m = a/b; let b = y1 - m*x1; { pointSlope: 'y - ' + y1 + ' = ' + m + '(x - ' + x1 + ')', slopeIntercept: 'y = ' + m + 'x + ' + b }`"
        },
        {
          "id": "PC-1.2c-I1",
          "type": "template",
          "objective": "Write an equation of a given line",
          "difficulty": "intermediate",
          "variables": {
            "x1": { "min": -10, "max": 10, "exclude": [0] },
            "y1": { "min": -10, "max": 10, "exclude": [0] },
            "x2": { "min": -10, "max": 10, "exclude": [0,"x1"] },
            "y2": { "min": -10, "max": 10, "exclude": [0, "y1"] }
          },
          "question": "Write the equation of the line passing through \\(({x1}, {y1})\\) and \\(({x2}, {y2})\\).",
          "answerFormula": "`let m = (y2 - y1)/(x2 - x1); let b = y1 - m*x1; 'y = ' + m + 'x + ' + b;`"
        },
        {
          "id": "PC-1.2c-A1",
          "type": "template",
          "objective": "Write an equation of a given line",
          "difficulty": "advanced",
          "variables": {
            "x1": { "min": -10, "max": 10, "exclude": [0] },
            "y1": { "min": -10, "max": 10, "exclude": [0] },
            "x2": { "min": -10, "max": 10, "exclude": [0,"x1"] },
            "y2": { "min": -10, "max": 10, "exclude": [0,"y1"] },
            "a": { "min": -5, "max": 5, "exclude": [0, "x1", "x2"] },
            "b": { "min": -5, "max": 5, "exclude": [0, "y1", "y2"] }
          },
          "question": "Find the equation of the line perpendicular to the line passing through \\(({x1}, {y1})\\) and \\(({x2}, {y2})\\) that also passes through the point \\(({a}, {b})\\).",
          "answerFormula": "`let m = (y2 - y1)/(x2 - x1); let mPerp = -1/m; 'y = ' + mPerp + 'x';`"
        },
        {
        "id": "PC-1.2d-B1",
        "type": "template",
        "objective": "Apply the distance and midpoint formula",
        "difficulty": "basic",
        "variables": {
          "x1": { "min": 1, "max": 5 },
          "y1": { "min": 1, "max": 5 },
          "x2": { "min": 6, "max": 10 },
          "y2": { "min": 6, "max": 10 }
        },
        "question": "Find the distance and midpoint between the points \\(({x1}, {y1})\\) and \\(({x2}, {y2})\\).",
        "answerFormula": "'Distance: ' + calculateDistance(x1, y1, x2, y2) + ', Midpoint: ' + formatCoordinate((x1 + x2)/2, (y1 + y2)/2)"
      },
      {
        "id": "PC-1.2d-I1",
        "type": "template",
        "objective": "Apply the distance and midpoint formula",
        "difficulty": "intermediate",
        "variables": {
          "x1": { "min": -6, "max": 6, "exclude": [0] },
          "y1": { "min": -6, "max": 6, "exclude": [0] },
          "x2": { "min": -6, "max": 6, "exclude": [0,"x1"] },
          "y2": { "min": -6, "max": 6, "exclude": [0,"y1"] }
        },
        "question": "Find the distance and midpoint between the points \\(({x1}, {y1})\\) and \\(({x2}, {y2})\\). Express your answer in simplified radical form.",
        "answerFormula": "'Distance: ' + calculateDistance(x1, y1, x2, y2) + ', Midpoint: ' + formatCoordinate((x1 + x2)/2, (y1 + y2)/2)"
      },
      {
        "id": "PC-1.2d-A2",
        "type": "template",
        "objective": "Apply the distance and midpoint formula",
        "difficulty": "advanced",
        "variables": {
          "x1": { "min": -8, "max": 8, "exclude": [0] },
          "y1": { "min": -8, "max": 8 ,"exclude": [0] },
          "y2": { "min": -8, "max": 8, "exclude": ["y1"] },
          "distance": { "min": 5, "max":15 }
        },
        "question": "The distance between \\( ({x1}, {y1})\\) and \\( (x, {y2}) \\) is {distance}. Find the missing coordinate.",
        "answerFormula": "`{ x: ( (distance**2) - (y2 - y1)**2 ) >= 0 ? (x1 + Math.sqrt((distance**2) - (y2 - y1)**2)) : 'No Real Solution', (x1 - Math.sqrt((distance**2) - (y2 - y1)**2)) }`"
      },
      {
        "id": "PC-1.3a-B1",
        "type": "template",
        "objective": "To write and graph absolute value and piecewise fuctions",
        "difficulty": "basic",
        "variables": {
          "a": { "min": -5, "max": 5, "exclude": [0] },
          "b": { "min": 2, "max": 7 },
          "c": { "min": 1, "max": 10}
        },
        "question": "Graph the absolute value function \\( f(x) = {a}|x - {b}| + {c} \\).",
        "answer": "V-shaped graph with vertex at \\(({b}, {c})\\) and slope \\({a}\\) on both sides."
      },
      {
        "id": "PC-1.3a-I1",
        "type": "template",
        "objective": "To write and graph absolute value and piecewise fuctions",
        "difficulty": "intermediate",
        "variables": {
          "a": { "min": -5, "max": 5, "exclude": [0] },
          "b": { "min": 2, "max": 7, "exclude": [0] },
          "c": { "min": 2, "max": 7, "exclude": [0] },
          "d": { "min": 1, "max": 10}
        },
        "question": "Graph the piecewise function: <br> \\( f(x) = \\begin{cases} {a}x + {b}, & x < 0 \\\\ {c}x^2 + {d}, & x \\geq 0 \\end{cases} \\).",
        "answer": "Graph with two pieces: a line with slope \\({a}\\) and y-intercept \\({b}\\) for \\(x < 0\\), and a parabola with vertex at \\((0, {d})\\) for \\(x \\geq 0\\)."
      },
      {
        "id": "PC-1.3b-B1",
        "type": "template",
        "objective": "To evaluate limits of functions at points of continuity and discontinuity",
        "difficulty": "basic",
        "variables": {
          "a": { "min": -5, "max": 5, "exclude": [0] },
          "b": { "min": 2, "max": 7 },
          "c": { "min": 1, "max": 10}
        },
        "question": "Evaluate the limit: \\( \\lim_{{x \\to {b}}} \\frac{{{a}x^2 - {c}}}{{x - {b}}} \\).",
        "answer": "{a}*{b} + {c}/{b}"
      },
      {
        "id": "PC-1.3b-I1",
        "type": "template",
        "objective": "To evaluate limits of functions at points of continuity and discontinuity",
        "difficulty": "intermediate",
        "variables": {
          "a": { "min": -5, "max": 5, "exclude": [0] },
          "b": { "min": 2, "max": 7, "exclude": [0] },
          "c": { "min": 2, "max": 7, "exclude": [0] },
          "d": { "min": 1, "max": 10}
        },
        "question": "Evaluate the limit: \\( \\lim_{{x \\to {b}}} \\frac{{{a}x^3 - {c}x^2 + {d}}}{{x^2 - {b}^2}} \\).",
        "answer": "{a}*{b}/2 - {c}/2"
      },
      {
        "id": "PC-1.3b-A1",
        "type": "template",
        "objective": "To evaluate limits of functions at points of continuity and discontinuity",
        "difficulty": "advanced",
        "variables": {
          "a": { "min": -5, "max": 5, "exclude": [0] },
          "b": { "min": 2, "max": 7, "exclude": [0] },
          "c": { "min": 2, "max": 7, "exclude": [0] },
          "d": { "min": 1, "max": 10}
        },
        "question": "Evaluate the limit: \\( \\lim_{{x \\to {b}}} \\frac{{{a}x^4 - {c}x^2 + {d}}}{{x^3 - {b}^3}} \\).",
        "answer": "{a}*{b}/3 - {c}/(3*{b})"
      },
      {
        "id": "PC-1.4a-B1",
        "type": "template",
        "objective": "Use limits to describe the end behavior of functions",
        "difficulty": "basic",
        "variables": {
          "a": { "min": -10, "max": 10, "exclude": [0] },
          "b": { "min": 2, "max": 3 }
        },
        "question": "Use limit notation to describe the end behavior of the power function without graphing \\( f(x) = {a}x^{b} \\).",
        "answer": "As \\( x \\to \\infty, f(x) \\to {a > 0 ? '\\infty' : '-\\infty'} \\); as \\( x \\to -\\infty, f(x) \\to {b % 2 === 0 ? (a > 0 ? '\\infty' : '-\\infty') : (a > 0 ? '-\\infty' : '\\infty')} \\)."
      },
      {
        "id": "PC-1.4a-I1",
        "type": "template",
        "objective": "Use limits to describe the end behavior of functions",
        "difficulty": "intermediate",
        "variables": {
          "a": { "min": -10, "max": 10, "exclude": [0] },
          "b": { "min": 2, "max": 4 },
          "c": { "min": -5, "max": 5 }
        },
        "question": "Use limit notation to describe the end behavior of the polynomial function without graphing \\( f(x) = {a}x^{b} + {c} \\).",
        "answer": "As \\( x \\to \\infty, f(x) \\to {a > 0 ? '\\infty' : '-\\infty'} \\); as \\( x \\to -\\infty, f(x) \\to {b % 2 === 0 ? (a > 0 ? '\\infty' : '-\\infty') : (a > 0 ? '-\\infty' : '\\infty')} \\)."
      },
      {
        "id": "PC-1.4b-B1",
        "type": "template",
        "objective": "Describe intervals in which a function is increasing, decreasing, or constant",
        "difficulty": "basic",
        "variables": {
          "a": { "values": [1, -1] },
          "b": { "min": 2, "max": 3 }
        },
        "question": "Describe the intervals in which the function \\( f(x) = {a}x^{b} \\) is increasing, decreasing, or constant.",
        "answer": "If {a > 0}, the function is increasing on \\\\((-\\\\infty, \\\\infty)\\\\). If {a < 0}, the function is decreasing on \\\\((-\\\\infty, \\\\infty)\\\\)."
      },
      {
        "id": "PC-1.4b-I1",
        "type": "template",
        "objective": "Describe intervals in which a function is increasing, decreasing, or constant",
        "difficulty": "intermediate",
        "variables": {
          "a": { "min": -10, "max": 10, "exclude": [0] },
          "b": { "min": -10, "max": 10, "exclude": [0, "a"] },
          "c": { "min": -10, "max": 10, "exclude": [0, "a", "b"] },
          "d": { "min": -10, "max": 10, "exclude": [0, "a", "b", "c"]}
        },
        "question": "Given the four power functions, state the end behavior: <br> \\( f(x) = {a}x^{2} \\), \\( g(x) = {b}x^{3} \\), \\( h(x) = {c}x^{4} \\), \\( k(x) = {d}x^{5} \\).",
        "answer": "\\( f(x) \\) is even; as \\( x \\to \\infty, f(x) \\to {a > 0 ? '\\infty' : '-\\infty'} \\); as \\( x \\to -\\infty, f(x) \\to {a > 0 ? '\\infty' : '-\\infty'} \\). <br> \\( g(x) \\) is odd; as \\( x \\to \\infty, g(x) \\to {b > 0 ? '\\infty' : '-\\infty'} \\); as \\( x \\to -\\infty, g(x) \\to {b > 0 ? '-\\infty' : '\\infty'} \\). <br> \\( h(x) \\) is even; as \\( x \\to \\infty, h(x) \\to {c > 0 ? '\\infty' : '-\\infty'} \\); as \\( x \\to -\\infty, h(x) \\to {c > 0 ? '\\infty' : '-\\infty'} \\). <br> \\( k(x) \\) is odd; as \\( x \\to \\infty, k(x) \\to {d > 0 ? '\\infty' : '-\\infty'} \\); as \\( x \\to -\\infty, k(x) \\to {d > 0 ? '-\\infty' : '\\infty'} \\)."
      },
      {
        "id": "PC-1.4c- B1",
        "type": "template",
        "objective": "Classify functions as even, odd, or neither",
        "difficulty": "basic",
        "variables": {
          "a": { "values": [1, -1, 2, -2] },
          "b": { "min": -3, "max": 3, "exclude":[0] }
        },
        "question": "Classify the function \\( f(x) = {a}x^2 + {b} \\) as even, odd, or neither.",
        "answer": "Even (symmetric about the y-axis)."
      },
      {
        "id": "PC-1.4c-I1",
        "type": "template",
        "objective": "Classify functions as even, odd, or neither",
        "difficulty": "intermediate",
        "variables": {
          "a": { "values": [1, -1, 2, -2] },
          "b": { "min": -3, "max": 3, "exclude":[0] },
          "c": { "min": -3, "max": 3, "exclude":[0] },
          "d": { "min": -3, "max": 3, "exclude":[0] },
          "e": { "min": -3, "max": 3, "exclude":[0] },
          "f": { "min": -3, "max": 3, "exclude":[0] }
        },
        "question": "Classify the following functions as even, odd, or neither: <br> \\( f(x) = {a}x^3 + {b}x \\) <br> \\( g(x) = {c}x^4 + {d}x^2 + {e} \\) <br> \\( h(x) = {f}x^5 + {b}x^3 + {a}x \\).",
        "answer": "\\( f(x) \\) is odd (symmetric about the origin). <br> \\( g(x) \\) is neither. <br> \\( h(x) \\) is odd (symmetric about the origin)."
      },
      {
        "id": "PC-1.5a-B1",
        "type": "template",
        "objective": "To graph transformations of parent functions",
        "difficulty": "basic",
        "variables": {
          "a": { "min": -5, "max": 5, "exclude": [0] },
          "b": { "min": 2, "max": 7 },
          "c": { "min": 1, "max": 10}
        },
        "question": "Without graphing the function \\( f(x) = {a}(x - {b})^2 + {c} \\). Identify the parent function and the transformations.",
        "answer": "Parent function: \\( f(x) = x^2 \\). Transformations: vertical stretch/compression by factor \\(|{a}|\\), reflection over x-axis if {a}<0, horizontal shift right {b} (if positive), left if negative, and vertical shift up {c} (if positive), down if negative."
      },
      {
        "id": "PC-1.5a-I1",
        "type": "template",
        "objective": "To graph transformations of parent functions",
        "difficulty": "intermediate",
        "variables": {
          "a": { "min": -5, "max": 5, "exclude": [0] },
          "b": { "min": 2, "max": 7, "exclude": [0] },
          "c": { "min": 2, "max": 7, "exclude": [0] },
          "d": { "min": 1, "max": 10}
        },
        "question": "Without graphing the function \\( f(x) = {a}\\sqrt{x - {b}} + {c} \\). Identify the parent function and the transformations.",
        "answer": "Parent function: \\( f(x) = \\sqrt{x} \\). Transformations: vertical stretch/compression by factor \\(|{a}|\\), reflection over x-axis if {a}<0, horizontal shift right {b} (if positive), left if negative, and vertical shift up {c} (if positive), down if negative."
      },
      {
        "id": "PC-1.5b-B1",
        "type": "template",
        "objective": "To write the equation of a transformed function",
        "difficulty": "basic",
        "variables": {
          "a": { "min": 2, "max": 5},
          "b": { "min": 2, "max": 7 },
          "c": { "min": 1, "max": 10}
        },
        "question": "Write the equation of the function that is a vertical stretch by a factor of \\({a}\\), reflected over the x-axis, shifted right {b}, and up {c} from the parent function \\( f(x) = x^2 \\).",
        "answer": "\\( f(x) = -{a}(x - {b})^2 + {c} \\)."
      },
      {
        "id": "PC-1.5b-I1",
        "type": "template",
        "objective": "To write the equation of a transformed function",
        "difficulty": "intermediate",
        "variables": {
          "a": { "min": 2, "max": 5 },
          "b": { "min": 2, "max": 7, "exclude": [0] },
          "c": { "min": 2, "max": 7, "exclude": [0] }
        },
        "question": "Write the equation of the function that is a vertical stretch by a factor of \\({a}\\), reflected over the y-axis, shifted right {b}, and up {c}, from the parent function \\( f(x) = \\sqrt{x} \\).",
        "answer": "\\( f(x) = -{a}\\sqrt{- (x - {b})} + {c} \\)."
      },
      {
        "id": "PC-1.6-B1",
        "type": "template",
        "objective": "To identify key features and graph quadratic functions",
        "difficulty": "basic",
        "variables": {
          "a": { "min": -5, "max": 5, "exclude": [0,1,-1] },
          "b": { "min": -10, "max": 10, "exclude": [0,1,-1] },
          "c": { "min": -10, "max": 10, "exclude": [0] }
        },
        "question": "Identify the vertex, axis of symmetry, and then graph the function with at least two points on each side of the vertex \\( f(x) = {a}x^2 + {b}x + {c} \\).",
        "answerFormula": "`let vertexX = -b/(2*a); let vertexY = a*vertexX**2 + b*vertexX + c; let axis = vertexX; { vertex: formatCoordinate(vertexX, vertexY), axisOfSymmetry: 'x = ' + axis }`"
      },
      {
        "id": "PC-1.6-I1",
        "type": "template",
        "objective": "To identify key features and graph quadratic functions",
        "difficulty": "intermediate",
        "variables": {
          "p": { "min": -8, "max": 8, "exclude": [0,1,-1] },
          "q": { "min": -4, "max": 4, "exclude": [0,1,-1] },
          "a": { "min": -4, "max": 4, "exclude": [0,1] },
          "b": { "formula": "a * q + p" },
          "c": { "formula": "p * q" }
        },
        "question": "Identify the x- and y-intercepts, and the coordinates of the vertex \\( f(x) = {a}x^2 + ({b})x + ({c}) \\).",
        "answerFormula": "(() => { const b = a * q + p; const c = p * q; const vertexX = -b / (2 * a); const vertexY = a * vertexX * vertexX + b * vertexX + c; const disc = b * b - 4 * a * c; if (Math.abs(disc) < 1e-9) { const r = -b / (2 * a); return `Vertex: (${vertexX.toFixed(3)}, ${vertexY.toFixed(3)}); x-intercept: (${r.toFixed(3)}, 0) (double root); y-intercept: (0, ${c})`; } else if (disc < 0) { return `Vertex: (${vertexX.toFixed(3)}, ${vertexY.toFixed(3)}); x-intercepts: none (complex roots); y-intercept: (0, ${c})`; } else { const r1 = (-b + Math.sqrt(disc)) / (2 * a); const r2 = (-b - Math.sqrt(disc)) / (2 * a); return `Vertex: (${vertexX.toFixed(3)}, ${vertexY.toFixed(3)}); x-intercepts: (${r1.toFixed(3)}, 0) and (${r2.toFixed(3)}, 0); y-intercept: (0, ${c})`; } })()"
      },
      {
        "id": "PC-1.6-A1",
        "type": "template",
        "objective": "To identify key features and graph quadratic functions",
        "difficulty": "advanced",
        "variables": {
          "a": { "min": -5, "max": 5, "exclude": [0,1] },
          "b": { "min": -10, "max": 10, "exclude": [0] },
          "c": { "min": -10, "max": 10, "exclude": [0] }
        },
        "question": "Identify the vertex and all zeros (real or complex) \\( f(x) = {a}x^2 + ({b})x + ({c}) \\).",
        "answerFormula": "`let vertexX = -b/(2*a); let vertexY = a*vertexX**2 + b*vertexX + c; let discriminant = b**2 - 4*a*c; let xIntercepts = discriminant > 0 ? [((-b + Math.sqrt(discriminant))/(2*a)).toFixed(2), ((-b - Math.sqrt(discriminant))/(2*a)).toFixed(2)] : discriminant === 0 ? [(-b/(2*a)).toFixed(2)] : ['No Real Roots, Complex Roots: ' + (-b/(2*a)).toFixed(2) + '  ' + (Math.sqrt(-discriminant)/(2*a)).toFixed(2) + 'i']; { vertex: formatCoordinate(vertexX, vertexY), xIntercepts: xIntercepts }`"
      },
      {
        "id": "PC-1.7-B1",
        "type": "template",
        "objective": "To perform function operations, compositions and decompositions and identify the resulting domain and range",
        "difficulty": "basic",
        "variables": {
          "a": { "min": 1, "max": 5 },
          "b": { "min": 1, "max": 5 }
        },
        "question": "Given \\( f(x) = {a}x + 2 \\) and \\( g(x) = {b}x^2 \\), find and simplify \\( (f + g)(x) \\).",
        "answer": "\\( (f + g)(x) = {a}x + 2 + {b}x^2 = {b}x^2 + {a}x + 2 \\)."
      },
      {
        "id": "PC-1.7-I1",
        "type": "template",
        "objective": "To perform function operations, compositions and decompositions and identify the resulting domain and range",
        "difficulty": "intermediate",
        "variables": {
          "a": { "min": 2, "max": 10 },
          "b": { "min": 2, "max": 10 },
          "c": { "min": 2, "max": 10 },
          "d": { "min": 2, "max": 10 }
        },
        "question": "Given \\( f(x) = {a}x + {b} \\) and \\( g(x) = {c}x^2 + {d} \\), find and simplify \\( (f \\circ g)(x) \\).",
        "answer": "\\( (f \\circ g)(x) = f(g(x)) = {a}({c}x^2 + {d}) + {b} = {a*c}x^2 + {a*d} + {b} \\)."
      },
      {
        "id": "PC-1.7-A1",
        "type": "template",
        "objective": "To perform function operations, compositions and decompositions and identify the resulting domain and range",
        "difficulty": "advanced",
        "variables": {
          "a": { "min": 2, "max": 10 },
          "b": { "min": 2, "max": 10 },
          "c": { "min": 2, "max": 10 },
          "d": { "min": 2, "max": 10 }
        },
        "question": "Given \\( f(x) = \\sqrt{{a}x + {b}} \\) and \\( g(x) = {c}x^2 + {d} \\), find and simplify \\( (g \\circ f)(x) \\), then state the composite function's domain and range.",
        "answer": "\\( (g \\circ f)(x) = g(f(x)) = {c}(\\sqrt{{a}x + {b}})^2 + {d} = {c}({a}x + {b}) + {d} = {a*c}x + {b*c} + {d} \\). <br> Domain: \\( x \\geq -{b}/{a} \\) if {a}>0, \\( x \\leq -{b}/{a} \\) if {a}<0. <br> Range: \\( [ {d}, \\infty ) \\) if {c}>0, \\( ( -\\infty, {d} ] \\) if {c}<0."
      },
      {
        "id": "PC-1.8a-B1",
        "type": "template",
        "objective": "To define relations and functions parametrically",
        "difficulty": "basic",
        "variables": {
          "a": { "min": 1, "max": 5 },
          "b": { "min": 1, "max": 5 }
        },
        "question": "Graph the function given the parametric equations <br> \\( x = t^2-{a} \\) <br> \\( y = {b}t + 1 \\) <br> for \\( t \\) in the interval \\( [-3, 3] \\).",
        "answer": "Parabola opening right with vertex at \\((-{a}, 1)\\) and slope {b}."
      },
      {
        "id": "PC-1.8a-I1",
        "type": "template",
        "objective": "To define relations and functions parametrically",
        "difficulty": "intermediate",
        "variables": {
          "a": { "min": 1, "max": 5 },
          "b": { "min": 1, "max": 5 },
          "c": { "min": 1, "max": 5 }
        },
        "question": "Graph the function given the parametric equations <br> \\( x = {a}t^2 - {b} \\) <br> \\( y = {c}t^3 + 2 \\) <br> for \\( t \\) in the interval \\( [-2, 2] \\).",
        "answer": "Cubic curve with inflection point at \\((-{b}, 2)\\) and vertical stretch by factor {c}."
      },
      {
        "id": "PC-1.8b-B1",
        "type": "template",
        "objective": "To identify, find an equation for, and graph inverses of a function",
        "difficulty": "basic",
        "variables": {
          "a": { "min": 2, "max": 5 },
          "b": { "min": 1, "max": 5 }
        },
        "question": "Find the inverse of the function \\( f(x) = {a}x + {b} \\) and state its domain and range.",
        "answer": "Inverse: \\( f^{-1}(x) = (x - {b})/{a} \\). <br> Domain: \\( (-\\infty, \\infty) \\), Range: \\( (-\\infty, \\infty) \\)."
      },
      {
        "id": "PC-1.8b-I1",
        "type": "template",
        "objective": "To identify, find an equation for, and graph inverses of a function",
        "difficulty": "intermediate",
        "variables": {
          "a": { "min": -5, "max": 5, "exclude": [0, 1] },
          "b": { "min": 1, "max": 5 },
          "c": { "min": 1, "max": 5 }
        },
        "question": "Find the inverse of the function \\( f(x) = {a}(x - {b})^2 + {c} \\) and state whether the result is a function or not.",
        "answer": "Inverse: \\( f^{-1}(x) = \\pm\\sqrt{(x - {c})/{a}} + {b} \\) (not a function unless domain is restricted)."
      },
      {
        "id": "PC-1.8b-A1",
        "type": "template",
        "objective": "To identify, find an equation for, and graph inverses of a function",
        "difficulty": "advanced",
        "variables": {
          "a": { "min": 1, "max": 5 },
          "b": { "min": 1, "max": 5 },
          "c": { "min": 1, "max": 5 }
        },
        "question": "Find the inverse of the function \\( f(x) = {a}x^2 + {b}x + {c} \\) and state its domain restrictions that would make the inverse a function.",
        "answer": "Inverse: \\( f^{-1}(x) = \\frac{-{b} \\pm \\sqrt{{b}^2 - 4{a}({c} - x)}}{2{a}} \\). Domain restriction: \\( x \\geq -{b}/(2{a}) \\) if {a}>0, \\( x \\leq -{b}/(2{a}) \\) if {a}<0."
      },
      {
        "id": "PC-1.8b-A2",
        "type": "template",
        "objective": "To identify, find an equation for, and graph inverses of a function",
        "difficulty": "advanced",
        "variables": {
          "a": { "min": 1, "max": 5 },
          "b": { "min": 1, "max": 5, "exclude": ["a"] }
        },
        "question": "Find the inverse of the function \\( f(x) = \\frac{{a}}{\\sqrt{ x - {b}}}.\\) and state its domain and range.",
        "answer": "Inverse: \\( f^{-1}(x) = {a}^2/x^2 + {b} \\). <br> Domain: \\( (0, \\infty) \\), Range: \\( ({b}, \\infty) \\)."
      }
      ],
      
      "Chapter 3": [
        {
          "id": "PC-3.1-I1",
          "type": "template",
          "objective": "Evaluate trigonometric functions",
          "difficulty": "intermediate",
          "variables": {
            "angle": { "values": [0, 30, 45, 60, 90] }
          },
          "question": "Evaluate \\( \\sin({angle}^{\\circ}) \\).",
          "answer": "Answer: \\( \\sin({angle}^{\\circ}) = {Math.sin(angle * Math.PI/180).toFixed(3)} \\)"
        },

        {
          "id": "PC-3.2-I1",
          "type": "template",
          "objective": "Graphing transformations of exponential functions",
          "difficulty": "intermediate",
          "variables": {
            "a": { "min": 1, "max": 3 },
            "b": { "values": [2, 3, 0.5] },
            "h": { "min": -3, "max": 3 },
            "k": { "min": -4, "max": 4 }
          },
          "question": "Graph the function \\( y = {a} \\cdot {b}^{x - {h}} + {k} \\). Identify the horizontal asymptote.",
          "answer": "The horizontal asymptote is \\( y = {k} \\)."
        },
        {
          "id": "PC-3.2-I2",
          "type": "template",
          "objective": "Graphing transformations of exponential functions",
          "difficulty": "intermediate",
          "variables": {
            "a": { "values": [1, -1, 2] },
            "b": { "values": [2, 0.5] },
            "h": { "min": -2, "max": 2 },
            "k": { "min": -3, "max": 3 }
          },
          "question": "Describe the transformations applied to \\( y = {b}^{x} \\) to obtain \\( y = {a}\\,{b}^{x - {h}} + {k} \\).",
          "answer": "Vertical stretch by factor \\(|{a}|\\), reflection over x-axis if {a}<0, horizontal shift right {h} (if positive), left if negative, and vertical shift up {k} (if positive), down if negative."
        },
        {
          "id": "PC-3.2-I3",
          "type": "template",
          "objective": "Graphing transformations of exponential functions",
          "difficulty": "intermediate",
          "variables": {
            "b": { "values": [2, 3] },
            "h": { "min": -4, "max": 4 },
            "k": { "min": -4, "max": 4 }
          },
          "question": "Find the y-intercept of \\( y = {b}^{x - {h}} + {k} \\).",
          "answer": "Substitute \\( x = 0 \\): \\( y = {b}^{- {h}} + {k} \\)."
        },
        {
          "id": "PC-3.2-I4",
          "type": "template",
          "objective": "Graphing transformations of exponential functions",
          "difficulty": "basic",
          "variables": {
            "a": { "min": 1, "max": 3 },
            "b": { "values": [2, 3, 0.5] },
            "h": { "min": -3, "max": 3 }
          },
          "question": "State the domain and range of \\( y = {a}{b}^{x - {h}} \\).",
          "answer": "Domain: \\( (-\\infty, \\infty) \\), Range: \\( (0, \\infty) \\) if {a}>0, \\( (-\\infty, 0) \\) if {a}<0."
        },
        {
          "id": "PC-3.2-I5",
          "type": "template",
          "objective": "Graphing transformations of exponential functions",
          "difficulty": "basic",
          "variables": {
            "b": { "values": [2, 3] },
            "k": { "min": -3, "max": 3 }
          },
          "question": "Multiple Choice: Which of the following is the horizontal asymptote of \\( y = {b}^{x} + {k} \\)?",
          "choices": [
            "\\( y = 0 \\)",
            "\\( y = {k} \\)",
            "\\( x = 0 \\)",
            "\\( x = {k} \\)"
          ],
          "answer": 1
        },
        {
          "id": "PC-3.2-I6",
          "type": "exponential",
          "objective": "Identifying transformations of exponential functions",
          "difficulty": "intermediate",
          "variables": {
            "a": { "values": [1] },
            "b": { "values": [2, 3] },
            "h": { "min": -3, "max": 3 },
            "k": { "min": -3, "max": 3 }
          },
          "question": "The graph of a transformed exponential function is shown below. Starting from the parent function \\( y = {b}^{x} \\), write the equation of the transformed function in the form \\( y = a({b})^{x - h} + k \\).",
          "answer": "\\( y = {a}({b})^{x - {h}} + {k} \\)",
          "draw": "exponential"
        }

      ],
    
      "Chapter 2": [
        {
        "id": "PC-1.1-I1",
        "type": "linearGraph",
        "objective": "Graph linear functions",
        "difficulty": "intermediate",
        "variables": {
          "m": { "values": [1, -1, 2, 0.5] },
          "b": { "values": [0, 1, -2] }
        },
        "question": "Graph the linear function \\( y = {m}x + {b} \\).",
        "answer": "A straight line with slope {m} and y-intercept {b}."
        },
        {
          "id": "PC-1.1-I2",
          "type": "parabola",
          "objective": "Graph quadratic functions",
          "difficulty": "intermediate",
          "variables": {
            "a": { "values": [1, -1, 2] },
            "b": { "values": [0, 1, -1] },
            "c": { "values": [0, -2, 3] }
          },
          "question": "Graph the quadratic function \\( y = {a}x^2 + {b}x + {c} \\).",
          "answer": "A parabola opening {a>0?'upward':'downward'} with vertex at \\(x = -{b}/(2{a})\\)."
        },
        {
          "id": "PC-1.1-I3",
          "type": "exponential",
          "objective": "Graph exponential functions",
          "difficulty": "intermediate",
          "variables": {
            "a": { "values": [1, 2] },
            "b": { "values": [2, 0.5] }
          },
          "question": "Graph the exponential function \\( y = {a} \\cdot {b}^{x} \\).",
          "answer": "An exponential curve passing through \\((0,{a})\\) with growth factor {b}."
        },
        {
          "id": "PC-1.1-I4",
          "type": "rational",
          "objective": "Graph rational functions",
          "difficulty": "intermediate",
          "variables": {
            "a": { "values": [1, -1] },
            "h": { "values": [0, 1] },
            "k": { "values": [0, -2] }
          },
          "question": "Graph the rational function \\( y = \\frac{{a}}{{x - {h}}} + {k} \\).",
          "answer": "A hyperbola with vertical asymptote \\(x = {h}\\) and horizontal asymptote \\(y = {k}\\)."
        },
        {
          "id": "PC-1.1-I5",
          "type": "trigSine",
          "objective": "Graph sine functions",
          "difficulty": "intermediate",
          "variables": {
            "a": { "values": [1, 2] },
            "b": { "values": [1, 2] },
            "c": { "values": [0, "Math.PI/2"] }
          },
          "question": "Graph the sine function \\( y = {a}\\sin({b}x + {c}) \\).",
          "answer": "A sine wave with amplitude {a} and period \\( \\frac{2\\pi}{{b}} \\)."
        },
        {
          "id": "PC-1.1-I6",
          "type": "trigCosine",
          "objective": "Graph cosine functions",
          "difficulty": "intermediate",
          "variables": {
            "a": { "values": [1, 2] },
            "b": { "values": [1, 2] },
            "c": { "values": [0, "Math.PI/2"] }
          },
          "question": "Graph the cosine function \\( y = {a}\\cos({b}x + {c}) \\).",
          "answer": "A cosine wave with amplitude {a} and period \\( \\frac{2\\pi}{{b}} \\)."
        }
      
      ]
    }
  
}
